{"BaseX":32096,"BaseY":31200,"BaseZ":8,"Items":[6684,4733,800,4727,4732,4729,4731,6683,6686,4730,6685,4728,6589,6580,6702,6583,6696,4564,4726,6706,4560,6695,4563,6701,6718,6698,4737,799,3413,4735,4736,6705,7150,7148,4559,6703,7153,6699,6700,4561,6697,6587,6716,6593,6591,6588,6582,7146,4600,7145,6966,7147,7106,4734,6717,4602,7149,7152,3050,6586,6714,4599,4562,6704,6590,4598,4597,285,6585,6707,7154,4601,6713,7151,6712,6592],"Explored":[65535,65535,65535,65535,65535,65535,65535,65535,65535,65535,0,0,0,0,0,0],"Map":[{"Items":[{"ID":6684},{"ID":4733}]},{"Items":[{"ID":800},{"ID":4727},{"ID":4732}]},{"Items":[{"ID":6684},{"ID":4729},{"ID":4731}]},{"Items":[{"ID":6683},{"ID":4729}]},{"Items":[{"ID":6684},{"ID":4729}]},{"Items":[{"ID":6686},{"ID":4730}]},{"Items":[{"ID":6684},{"ID":4733}],"Creatures":[{"Header":97,"UKHeader":0,"ID":1074228757,"CreatureType":1,"CharNameLength":8,"CharName":"gargoyle","HealthPercent":100,"Direction":0,"Outfit":95,"ColorHead":0,"ColorBody":0,"ColorLegs":0,"ColorFeet":0,"Addons":0,"Mount":0,"LightRadius":0,"LightColor":0,"Speed":100,"Skull":0,"PartyShield":0,"GuildShield":0,"UKEnd1":0,"UKEnd2":0,"UKEnd3":1,"UKEnd4":0,"UKEnd5":255,"UKEnd6":0,"UKEnd7":0,"UKEnd8":1}]},{"Items":[{"ID":6685},{"ID":4728},{"ID":4731}]},{"Items":[{"ID":6589}]},{"Items":[{"ID":6580},{"ID":6702}]},{"Items":[{"ID":6583},{"ID":6702},{"ID":6696}]},{"Items":[{"ID":4564},{"ID":4726},{"ID":6706}]},{"Items":[{"ID":6685}]},{"Items":[{"ID":4560},{"ID":6695}]},{"Items":[{"ID":4563},{"ID":6702},{"ID":6701},{"ID":6718}]},{"Items":[{"ID":4563},{"ID":6706},{"ID":6698}]},{"Items":[{"ID":6685},{"ID":4737}]},{"Items":[{"ID":799}]},{"Items":[{"ID":6686},{"ID":4726}]},{"Items":[{"ID":6683}]},{"Items":[{"ID":800}]},{"Items":[{"ID":6683},{"ID":4733}]},{"Items":[{"ID":6684},{"ID":4737},{"ID":3413}]},{"Items":[{"ID":800},{"ID":4727},{"ID":4732},{"ID":4735}]},{"Items":[{"ID":6685},{"ID":4736},{"ID":4727}]},{"Items":[{"ID":799},{"ID":6701}]},{"Items":[{"ID":799},{"ID":6705},{"ID":7150}]},{"Items":[{"ID":6683},{"ID":7148}]},{"Items":[{"ID":4559},{"ID":6703},{"ID":6696},{"ID":7153}]},{"Items":[{"ID":4559},{"ID":6699},{"ID":6700}]},{"Items":[{"ID":4561},{"ID":6697},{"ID":4733}]},{"Items":[{"ID":6684},{"ID":4727}]},{"Items":[{"ID":6587},{"ID":6716}]},{"Items":[{"ID":799}]},{"Items":[{"ID":6684},{"ID":4726}]},{"Items":[{"ID":6686}]},{"Items":[{"ID":6686},{"ID":4733}]},{"Items":[{"ID":6686},{"ID":4737}]},{"Items":[{"ID":6593},{"ID":4735}]},{"Items":[{"ID":6591}]},{"Items":[{"ID":6588}]},{"Items":[{"ID":799}]},{"Items":[{"ID":6582},{"ID":6701},{"ID":7146}]},{"Items":[{"ID":4600,"AnimationStep":0},{"ID":4726},{"ID":6705},{"ID":7145},{"ID":6966}]},{"Items":[{"ID":6686},{"ID":7147}]},{"Items":[{"ID":4563},{"ID":6695}]},{"Items":[{"ID":4561},{"ID":6701},{"ID":4728}]},{"Items":[{"ID":6580}]},{"Items":[{"ID":6580},{"ID":7106,"AnimationStep":0}]},{"Items":[{"ID":6684},{"ID":4734}]},{"Items":[{"ID":6684},{"ID":4730},{"ID":4733}]},{"Items":[{"ID":6685},{"ID":4731}]},{"Items":[{"ID":6683},{"ID":4732}]},{"Items":[{"ID":6686},{"ID":4736},{"ID":6717}]},{"Items":[{"ID":6684},{"ID":4729},{"ID":4734}]},{"Items":[{"ID":6684},{"ID":4729}]},{"Items":[{"ID":6686},{"ID":4736}]},{"Items":[{"ID":799}]},{"Items":[{"ID":6582}]},{"Items":[{"ID":4602,"AnimationStep":0},{"ID":6697},{"ID":4726},{"ID":7149},{"ID":6966}]},{"Items":[{"ID":6684},{"ID":7152}]},{"Items":[{"ID":4561},{"ID":6695},{"ID":4733},{"ID":3413},{"ID":3050}]},{"Items":[{"ID":4564},{"ID":4737}]},{"Items":[{"ID":6586}]},{"Items":[{"ID":6686},{"ID":4729},{"ID":6714}]},{"Items":[{"ID":6684},{"ID":4730},{"ID":4733}]},{"Items":[{"ID":6684},{"ID":4737}]},{"Items":[{"ID":6683},{"ID":4735}]},{"Items":[{"ID":6686},{"ID":4731}]},{"Items":[{"ID":800},{"ID":4733},{"ID":4732}]},{"Items":[{"ID":6684},{"ID":4731},{"ID":4730}]},{"Items":[{"ID":6684}]},{"Items":[{"ID":800},{"ID":4728}]},{"Items":[{"ID":799}]},{"Items":[{"ID":6684},{"ID":4727},{"ID":4726},{"ID":4728},{"ID":4729}]},{"Items":[{"ID":4599,"AnimationStep":0},{"ID":6697},{"ID":4726}]},{"Items":[{"ID":6686},{"ID":4733}]},{"Items":[{"ID":4562},{"ID":6704},{"ID":4737}]},{"Items":[{"ID":6590}]},{"Items":[{"ID":6582}]},{"Items":[{"ID":4598,"AnimationStep":0},{"ID":6705},{"ID":4727}]},{"Items":[{"ID":6684},{"ID":4737}]},{"Items":[{"ID":6586}]},{"Items":[{"ID":6683},{"ID":4734}]},{"Items":[{"ID":6684},{"ID":4730},{"ID":4733}]},{"Items":[{"ID":800},{"ID":4737}]},{"Items":[{"ID":6684},{"ID":4727},{"ID":4726}]},{"Items":[{"ID":6685},{"ID":4727}]},{"Items":[{"ID":6686},{"ID":4737}]},{"Items":[{"ID":799}]},{"Items":[{"ID":6593},{"ID":6966}]},{"Items":[{"ID":4597,"AnimationStep":0},{"ID":6697},{"ID":4726}]},{"Items":[{"ID":6684},{"ID":4728}]},{"Items":[{"ID":799},{"ID":285,"Count":1}]},{"Items":[{"ID":6684},{"ID":4727},{"ID":4726},{"ID":4728},{"ID":4729}]},{"Items":[{"ID":6684},{"ID":4726},{"ID":4736}]},{"Items":[{"ID":799}]},{"Items":[{"ID":799}]},{"Items":[{"ID":6586}]},{"Items":[{"ID":6683},{"ID":4735}]},{"Items":[{"ID":800},{"ID":4728},{"ID":4731}]},{"Items":[{"ID":6580}]},{"Items":[{"ID":799}]},{"Items":[{"ID":6587}]},{"Items":[{"ID":6588}]},{"Items":[{"ID":799}]},{"Items":[{"ID":6585},{"ID":6707}]},{"Items":[{"ID":4597,"AnimationStep":0},{"ID":6697},{"ID":4726},{"ID":4733},{"ID":6966}]},{"Items":[{"ID":6685},{"ID":4737}]},{"Items":[{"ID":799}]},{"Items":[{"ID":6593}]},{"Items":[{"ID":6685},{"ID":4726},{"ID":4728}]},{"Items":[{"ID":4599,"AnimationStep":0},{"ID":6702},{"ID":4734}]},{"Items":[{"ID":4597,"AnimationStep":0},{"ID":6696},{"ID":4729}]},{"Items":[{"ID":4599,"AnimationStep":0},{"ID":6700},{"ID":4736},{"ID":6718}]},{"Items":[{"ID":799}]},{"Items":[{"ID":800},{"ID":4732},{"ID":4735}]},{"Items":[{"ID":800},{"ID":4736},{"ID":4727},{"ID":4733}]},{"Items":[{"ID":6580}]},{"Items":[{"ID":4598,"AnimationStep":0},{"ID":6702},{"ID":4734},{"ID":6966}]},{"Items":[{"ID":4598,"AnimationStep":0},{"ID":6696},{"ID":4729}]},{"Items":[{"ID":4602,"AnimationStep":0},{"ID":6696},{"ID":4729},{"ID":7150}]},{"Items":[{"ID":4602,"AnimationStep":0},{"ID":6696},{"ID":4729},{"ID":7154},{"ID":6966}]},{"Items":[{"ID":4597,"AnimationStep":0},{"ID":6706},{"ID":4730},{"ID":4728},{"ID":7147}]},{"Items":[{"ID":6593}]},{"Items":[{"ID":4559},{"ID":4729},{"ID":4735}]},{"Items":[{"ID":4559},{"ID":6697},{"ID":4729},{"ID":4731},{"ID":285,"Count":2}]},{"Items":[{"ID":6685},{"ID":4730},{"ID":4728}]},{"Items":[{"ID":4600,"AnimationStep":0},{"ID":4726},{"ID":6697},{"ID":6700}]},{"Items":[{"ID":6684},{"ID":6707}]},{"Items":[{"ID":4601,"AnimationStep":0},{"ID":6695},{"ID":4732}]},{"Items":[{"ID":4598,"AnimationStep":0},{"ID":4736},{"ID":6966}]},{"Items":[{"ID":799}]},{"Items":[{"ID":6587}]},{"Items":[{"ID":4601,"AnimationStep":0},{"ID":4734},{"ID":6713}]},{"Items":[{"ID":4599,"AnimationStep":0},{"ID":6697},{"ID":4730}]},{"Items":[{"ID":800}]},{"Items":[{"ID":6684},{"ID":7151}]},{"Items":[{"ID":800},{"ID":7149},{"ID":7151}]},{"Items":[{"ID":6684},{"ID":4732},{"ID":7152}]},{"Items":[{"ID":6683},{"ID":4728},{"ID":4736}]},{"Items":[{"ID":6588},{"ID":285,"Count":2}]},{"Items":[{"ID":4560},{"ID":6701},{"ID":4735}]},{"Items":[{"ID":4560},{"ID":6698},{"ID":4737}]},{"Items":[{"ID":4599,"AnimationStep":0},{"ID":6701},{"ID":4730},{"ID":6695}]},{"Items":[{"ID":4597,"AnimationStep":0},{"ID":6702},{"ID":6698}]},{"Items":[{"ID":4601,"AnimationStep":0},{"ID":6696},{"ID":6699}]},{"Items":[{"ID":4599,"AnimationStep":0},{"ID":6696},{"ID":4732}]},{"Items":[{"ID":4597,"AnimationStep":0},{"ID":6696},{"ID":4729}]},{"Items":[{"ID":4600,"AnimationStep":0},{"ID":6696},{"ID":4729}]},{"Items":[{"ID":4599,"AnimationStep":0},{"ID":6696},{"ID":4730}]},{"Items":[{"ID":4600,"AnimationStep":0},{"ID":6706},{"ID":6712}]},{"Items":[{"ID":6683}]},{"Items":[{"ID":6684}]},{"Items":[{"ID":6685}]},{"Items":[{"ID":6684},{"ID":4733}]},{"Items":[{"ID":6684},{"ID":4737},{"ID":7150}]},{"Items":[{"ID":799}]},{"Items":[{"ID":6592}]},{"Items":[{"ID":799},{"ID":6707}]}]}