{"BaseX":32800,"BaseY":31984,"BaseZ":8,"Items":[353,4551,351,4546,5642,5645,4559,1950,4555,5641,101,354,4547,378,376,379,5726,5714,5643,380,374,5713,5711,5712],"Explored":[2047,2047,2047,8191,16383,16383,16383,16383,16383,16383,16383,16383,16383,16383,16383,16383],"Map":[{"Items":[{"ID":353},{"ID":4551}]},{"Items":[{"ID":351},{"ID":4546},{"ID":5642}]},{"Items":[{"ID":351},{"ID":5645}]},{"Items":[{"ID":4559},{"ID":1950}]},{"Items":[{"ID":4555},{"ID":5641}]},{"Items":[{"ID":101}]},{"Items":[{"ID":101}]},{"Items":[{"ID":101}]},{"Items":[{"ID":101}]},{"Items":[{"ID":101}]},{"Items":[{"ID":101}]},{"Items":[{"ID":354},{"ID":4547}]},{"Items":[{"ID":351},{"ID":5641}]},{"Items":[{"ID":378}]},{"Items":[{"ID":376}]},{"Items":[{"ID":379}]},{"Items":[{"ID":101}]},{"Items":[{"ID":101}]},{"Items":[{"ID":101}]},{"Items":[{"ID":101}]},{"Items":[{"ID":101}]},{"Items":[{"ID":101}]},{"Items":[{"ID":354}]},{"Items":[{"ID":351},{"ID":5641}]},{"Items":[{"ID":101}]},{"Items":[{"ID":101}]},{"Items":[{"ID":101}]},{"Items":[{"ID":5726}]},{"Items":[{"ID":101}]},{"Items":[{"ID":101}]},{"Items":[{"ID":101}]},{"Items":[{"ID":5714}]},{"Items":[{"ID":5726}]},{"Items":[{"ID":351}]},{"Items":[{"ID":351},{"ID":5643}]},{"Items":[{"ID":380}]},{"Items":[{"ID":101}]},{"Items":[{"ID":101}]},{"Items":[{"ID":101}]},{"Items":[{"ID":101}]},{"Items":[{"ID":101}]},{"Items":[{"ID":101}]},{"Items":[{"ID":101}]},{"Items":[{"ID":101}]},{"Items":[{"ID":5726}]},{"Items":[{"ID":101}]},{"Items":[{"ID":351}]},{"Items":[{"ID":353}]},{"Items":[{"ID":374}]},{"Items":[{"ID":101}]},{"Items":[{"ID":5713}]},{"Items":[{"ID":5711}]},{"Items":[{"ID":5712}]},{"Items":[{"ID":101}]},{"Items":[{"ID":101}]},{"Items":[{"ID":101}]},{"Items":[{"ID":101}]},{"Items":[{"ID":101}]},{"Items":[{"ID":101}]},{"Items":[{"ID":101}]},{"Items":[{"ID":101}]},{"Items":[{"ID":101}]},{"Items":[{"ID":101}]},{"Items":[{"ID":101}]},{"Items":[{"ID":101}]},{"Items":[{"ID":101}]},{"Items":[{"ID":101}]},{"Items":[{"ID":101}]},{"Items":[{"ID":101}]},{"Items":[{"ID":101}]},{"Items":[{"ID":101}]},{"Items":[{"ID":101}]},{"Items":[{"ID":101}]},{"Items":[{"ID":101}]},{"Items":[{"ID":101}]},{"Items":[{"ID":101}]},{"Items":[{"ID":101}]},{"Items":[{"ID":101}]},{"Items":[{"ID":101}]},{"Items":[{"ID":101}]},{"Items":[{"ID":101}]},{"Items":[{"ID":101}]},{"Items":[{"ID":101}]},{"Items":[{"ID":101}]},{"Items":[{"ID":101}]},{"Items":[{"ID":101}]},{"Items":[{"ID":101}]},{"Items":[{"ID":101}]},{"Items":[{"ID":101}]},{"Items":[{"ID":101}]},{"Items":[{"ID":101}]},{"Items":[{"ID":101}]},{"Items":[{"ID":101}]},{"Items":[{"ID":101}]},{"Items":[{"ID":101}]},{"Items":[{"ID":101}]},{"Items":[{"ID":101}]},{"Items":[{"ID":101}]},{"Items":[{"ID":101}]},{"Items":[{"ID":101}]},{"Items":[{"ID":101}]},{"Items":[{"ID":101}]},{"Items":[{"ID":101}]},{"Items":[{"ID":101}]},{"Items":[{"ID":101}]},{"Items":[{"ID":101}]},{"Items":[{"ID":101}]},{"Items":[{"ID":101}]},{"Items":[{"ID":101}]},{"Items":[{"ID":101}]},{"Items":[{"ID":101}]},{"Items":[{"ID":101}]},{"Items":[{"ID":101}]},{"Items":[{"ID":101}]},{"Items":[{"ID":101}]},{"Items":[{"ID":101}]},{"Items":[{"ID":101}]},{"Items":[{"ID":101}]},{"Items":[{"ID":101}]},{"Items":[{"ID":101}]},{"Items":[{"ID":101}]},{"Items":[{"ID":101}]},{"Items":[{"ID":101}]},{"Items":[{"ID":101}]},{"Items":[{"ID":101}]},{"Items":[{"ID":101}]},{"Items":[{"ID":101}]},{"Items":[{"ID":101}]},{"Items":[{"ID":101}]},{"Items":[{"ID":5726}]},{"Items":[{"ID":101}]},{"Items":[{"ID":101}]},{"Items":[{"ID":101}]},{"Items":[{"ID":101}]},{"Items":[{"ID":101}]},{"Items":[{"ID":101}]},{"Items":[{"ID":101}]},{"Items":[{"ID":101}]},{"Items":[{"ID":101}]},{"Items":[{"ID":101}]},{"Items":[{"ID":101}]},{"Items":[{"ID":101}]},{"Items":[{"ID":101}]},{"Items":[{"ID":101}]},{"Items":[{"ID":101}]},{"Items":[{"ID":101}]},{"Items":[{"ID":101}]},{"Items":[{"ID":101}]},{"Items":[{"ID":101}]},{"Items":[{"ID":101}]},{"Items":[{"ID":101}]},{"Items":[{"ID":101}]},{"Items":[{"ID":101}]},{"Items":[{"ID":101}]},{"Items":[{"ID":101}]},{"Items":[{"ID":101}]},{"Items":[{"ID":101}]},{"Items":[{"ID":101}]},{"Items":[{"ID":101}]},{"Items":[{"ID":101}]},{"Items":[{"ID":101}]},{"Items":[{"ID":101}]},{"Items":[{"ID":101}]},{"Items":[{"ID":101}]},{"Items":[{"ID":101}]},{"Items":[{"ID":101}]},{"Items":[{"ID":101}]},{"Items":[{"ID":101}]},{"Items":[{"ID":101}]},{"Items":[{"ID":101}]},{"Items":[{"ID":101}]},{"Items":[{"ID":101}]},{"Items":[{"ID":101}]},{"Items":[{"ID":101}]},{"Items":[{"ID":101}]},{"Items":[{"ID":101}]},{"Items":[{"ID":101}]},{"Items":[{"ID":101}]},{"Items":[{"ID":101}]},{"Items":[{"ID":101}]},{"Items":[{"ID":101}]},{"Items":[{"ID":101}]},{"Items":[{"ID":101}]},{"Items":[{"ID":101}]},{"Items":[{"ID":101}]},{"Items":[{"ID":101}]},{"Items":[{"ID":101}]},{"Items":[{"ID":101}]},{"Items":[{"ID":101}]},{"Items":[{"ID":101}]},{"Items":[{"ID":101}]},{"Items":[{"ID":101}]},{"Items":[{"ID":101}]},{"Items":[{"ID":101}]},{"Items":[{"ID":101}]},{"Items":[{"ID":101}]},{"Items":[{"ID":101}]},{"Items":[{"ID":101}]},{"Items":[{"ID":101}]},{"Items":[{"ID":101}]},{"Items":[{"ID":101}]},{"Items":[{"ID":101}]},{"Items":[{"ID":101}]},{"Items":[{"ID":101}]},{"Items":[{"ID":101}]},{"Items":[{"ID":101}]},{"Items":[{"ID":101}]},{"Items":[{"ID":101}]},{"Items":[{"ID":101}]},{"Items":[{"ID":101}]},{"Items":[{"ID":101}]},{"Items":[{"ID":101}]},{"Items":[{"ID":101}]},{"Items":[{"ID":101}]}]}