{"BaseX":33136,"BaseY":31232,"BaseZ":10,"Items":[1128],"Explored":[65535,65535,65535,65535,65535,65535,65533,57345,57345,57345,57345,57345,57345,57345,57345,57345],"Map":[{"Items":[{"ID":1128}]},{"Items":[{"ID":1128}]},{"Items":[{"ID":1128}]},{"Items":[{"ID":1128}]},{"Items":[{"ID":1128}]},{"Items":[{"ID":1128}]},{"Items":[{"ID":1128}]},{"Items":[{"ID":1128}]},{"Items":[{"ID":1128}]},{"Items":[{"ID":1128}]},{"Items":[{"ID":1128}]},{"Items":[{"ID":1128}]},{"Items":[{"ID":1128}]},{"Items":[{"ID":1128}]},{"Items":[{"ID":1128}]},{"Items":[{"ID":1128}]},{"Items":[{"ID":1128}]},{"Items":[{"ID":1128}]},{"Items":[{"ID":1128}]},{"Items":[{"ID":1128}]},{"Items":[{"ID":1128}]},{"Items":[{"ID":1128}]},{"Items":[{"ID":1128}]},{"Items":[{"ID":1128}]},{"Items":[{"ID":1128}]},{"Items":[{"ID":1128}]},{"Items":[{"ID":1128}]},{"Items":[{"ID":1128}]},{"Items":[{"ID":1128}]},{"Items":[{"ID":1128}]},{"Items":[{"ID":1128}]},{"Items":[{"ID":1128}]},{"Items":[{"ID":1128}]},{"Items":[{"ID":1128}]},{"Items":[{"ID":1128}]},{"Items":[{"ID":1128}]},{"Items":[{"ID":1128}]},{"Items":[{"ID":1128}]},{"Items":[{"ID":1128}]},{"Items":[{"ID":1128}]},{"Items":[{"ID":1128}]},{"Items":[{"ID":1128}]},{"Items":[{"ID":1128}]},{"Items":[{"ID":1128}]},{"Items":[{"ID":1128}]},{"Items":[{"ID":1128}]},{"Items":[{"ID":1128}]},{"Items":[{"ID":1128}]},{"Items":[{"ID":1128}]},{"Items":[{"ID":1128}]},{"Items":[{"ID":1128}]},{"Items":[{"ID":1128}]},{"Items":[{"ID":1128}]},{"Items":[{"ID":1128}]},{"Items":[{"ID":1128}]},{"Items":[{"ID":1128}]},{"Items":[{"ID":1128}]},{"Items":[{"ID":1128}]},{"Items":[{"ID":1128}]},{"Items":[{"ID":1128}]},{"Items":[{"ID":1128}]},{"Items":[{"ID":1128}]},{"Items":[{"ID":1128}]},{"Items":[{"ID":1128}]},{"Items":[{"ID":1128}]},{"Items":[{"ID":1128}]},{"Items":[{"ID":1128}]},{"Items":[{"ID":1128}]},{"Items":[{"ID":1128}]},{"Items":[{"ID":1128}]},{"Items":[{"ID":1128}]},{"Items":[{"ID":1128}]},{"Items":[{"ID":1128}]},{"Items":[{"ID":1128}]},{"Items":[{"ID":1128}]},{"Items":[{"ID":1128}]},{"Items":[{"ID":1128}]},{"Items":[{"ID":1128}]},{"Items":[{"ID":1128}]},{"Items":[{"ID":1128}]},{"Items":[{"ID":1128}]},{"Items":[{"ID":1128}]},{"Items":[{"ID":1128}]},{"Items":[{"ID":1128}]},{"Items":[{"ID":1128}]},{"Items":[{"ID":1128}]},{"Items":[{"ID":1128}]},{"Items":[{"ID":1128}]},{"Items":[{"ID":1128}]},{"Items":[{"ID":1128}]},{"Items":[{"ID":1128}]},{"Items":[{"ID":1128}]},{"Items":[{"ID":1128}]},{"Items":[{"ID":1128}]},{"Items":[{"ID":1128}]},{"Items":[{"ID":1128}]},{"Items":[{"ID":1128}]},{"Items":[{"ID":1128}]},{"Items":[{"ID":1128}]},{"Items":[{"ID":1128}]},{"Items":[{"ID":1128}]},{"Items":[{"ID":1128}]},{"Items":[{"ID":1128}]},{"Items":[{"ID":1128}]},{"Items":[{"ID":1128}]},{"Items":[{"ID":1128}]},{"Items":[{"ID":1128}]},{"Items":[{"ID":1128}]},{"Items":[{"ID":1128}]},{"Items":[{"ID":1128}]},{"Items":[{"ID":1128}]},{"Items":[{"ID":1128}]},{"Items":[{"ID":1128}]},{"Items":[{"ID":1128}]},{"Items":[{"ID":1128}]},{"Items":[{"ID":1128}]},{"Items":[{"ID":1128}]},{"Items":[{"ID":1128}]},{"Items":[{"ID":1128}]},{"Items":[{"ID":1128}]},{"Items":[{"ID":1128}]},{"Items":[{"ID":1128}]},{"Items":[{"ID":1128}]},{"Items":[{"ID":1128}]},{"Items":[{"ID":1128}]},{"Items":[{"ID":1128}]},{"Items":[{"ID":1128}]},{"Items":[{"ID":1128}]},{"Items":[{"ID":1128}]},{"Items":[{"ID":1128}]},{"Items":[{"ID":1128}]},{"Items":[{"ID":1128}]},{"Items":[{"ID":1128}]},{"Items":[{"ID":1128}]},{"Items":[{"ID":1128}]},{"Items":[{"ID":1128}]},{"Items":[{"ID":1128}]},{"Items":[{"ID":1128}]},{"Items":[{"ID":1128}]},{"Items":[{"ID":1128}]},{"Items":[{"ID":1128}]},{"Items":[{"ID":1128}]},{"Items":[{"ID":1128}]},{"Items":[{"ID":1128}]},{"Items":[{"ID":1128}]},{"Items":[{"ID":1128}]},{"Items":[{"ID":1128}]}]}