{"BaseX":33024,"BaseY":32192,"BaseZ":10,"Items":[101,377,3713,381,3716,373,3718,353,354],"Explored":[65535,65535,65535,65535,65535,65535,65535,65535,65535,65535,65535,65535,65535,65535,65535,65535],"Map":[{"Items":[{"ID":101}]},{"Items":[{"ID":101}]},{"Items":[{"ID":101}]},{"Items":[{"ID":101}]},{"Items":[{"ID":101}]},{"Items":[{"ID":101}]},{"Items":[{"ID":101}]},{"Items":[{"ID":101}]},{"Items":[{"ID":101}]},{"Items":[{"ID":101}]},{"Items":[{"ID":101}]},{"Items":[{"ID":101}]},{"Items":[{"ID":101}]},{"Items":[{"ID":101}]},{"Items":[{"ID":101}]},{"Items":[{"ID":101}]},{"Items":[{"ID":101}]},{"Items":[{"ID":101}]},{"Items":[{"ID":101}]},{"Items":[{"ID":101}]},{"Items":[{"ID":101}]},{"Items":[{"ID":101}]},{"Items":[{"ID":101}]},{"Items":[{"ID":101}]},{"Items":[{"ID":101}]},{"Items":[{"ID":101}]},{"Items":[{"ID":101}]},{"Items":[{"ID":101}]},{"Items":[{"ID":101}]},{"Items":[{"ID":101}]},{"Items":[{"ID":101}]},{"Items":[{"ID":101}]},{"Items":[{"ID":101}]},{"Items":[{"ID":101}]},{"Items":[{"ID":101}]},{"Items":[{"ID":101}]},{"Items":[{"ID":101}]},{"Items":[{"ID":101}]},{"Items":[{"ID":101}]},{"Items":[{"ID":101}]},{"Items":[{"ID":101}]},{"Items":[{"ID":101}]},{"Items":[{"ID":101}]},{"Items":[{"ID":101}]},{"Items":[{"ID":101}]},{"Items":[{"ID":101}]},{"Items":[{"ID":101}]},{"Items":[{"ID":101}]},{"Items":[{"ID":101}]},{"Items":[{"ID":101}]},{"Items":[{"ID":101}]},{"Items":[{"ID":101}]},{"Items":[{"ID":101}]},{"Items":[{"ID":101}]},{"Items":[{"ID":101}]},{"Items":[{"ID":101}]},{"Items":[{"ID":101}]},{"Items":[{"ID":101}]},{"Items":[{"ID":101}]},{"Items":[{"ID":101}]},{"Items":[{"ID":101}]},{"Items":[{"ID":101}]},{"Items":[{"ID":101}]},{"Items":[{"ID":101}]},{"Items":[{"ID":101}]},{"Items":[{"ID":101}]},{"Items":[{"ID":101}]},{"Items":[{"ID":101}]},{"Items":[{"ID":101}]},{"Items":[{"ID":101}]},{"Items":[{"ID":101}]},{"Items":[{"ID":101}]},{"Items":[{"ID":101}]},{"Items":[{"ID":101}]},{"Items":[{"ID":101}]},{"Items":[{"ID":101}]},{"Items":[{"ID":101}]},{"Items":[{"ID":101}]},{"Items":[{"ID":101}]},{"Items":[{"ID":101}]},{"Items":[{"ID":101}]},{"Items":[{"ID":101}]},{"Items":[{"ID":101}]},{"Items":[{"ID":101}]},{"Items":[{"ID":101}]},{"Items":[{"ID":101}]},{"Items":[{"ID":101}]},{"Items":[{"ID":101}]},{"Items":[{"ID":101}]},{"Items":[{"ID":101}]},{"Items":[{"ID":101}]},{"Items":[{"ID":101}]},{"Items":[{"ID":101}]},{"Items":[{"ID":101}]},{"Items":[{"ID":101}]},{"Items":[{"ID":101}]},{"Items":[{"ID":101}]},{"Items":[{"ID":101}]},{"Items":[{"ID":101}]},{"Items":[{"ID":101}]},{"Items":[{"ID":101}]},{"Items":[{"ID":101}]},{"Items":[{"ID":101}]},{"Items":[{"ID":101}]},{"Items":[{"ID":101}]},{"Items":[{"ID":101}]},{"Items":[{"ID":101}]},{"Items":[{"ID":101}]},{"Items":[{"ID":101}]},{"Items":[{"ID":101}]},{"Items":[{"ID":101}]},{"Items":[{"ID":101}]},{"Items":[{"ID":101}]},{"Items":[{"ID":101}]},{"Items":[{"ID":101}]},{"Items":[{"ID":101}]},{"Items":[{"ID":101}]},{"Items":[{"ID":101}]},{"Items":[{"ID":101}]},{"Items":[{"ID":101}]},{"Items":[{"ID":101}]},{"Items":[{"ID":101}]},{"Items":[{"ID":101}]},{"Items":[{"ID":101}]},{"Items":[{"ID":101}]},{"Items":[{"ID":101}]},{"Items":[{"ID":101}]},{"Items":[{"ID":101}]},{"Items":[{"ID":101}]},{"Items":[{"ID":101}]},{"Items":[{"ID":101}]},{"Items":[{"ID":101}]},{"Items":[{"ID":101}]},{"Items":[{"ID":101}]},{"Items":[{"ID":101}]},{"Items":[{"ID":101}]},{"Items":[{"ID":101}]},{"Items":[{"ID":101}]},{"Items":[{"ID":101}]},{"Items":[{"ID":101}]},{"Items":[{"ID":101}]},{"Items":[{"ID":101}]},{"Items":[{"ID":101}]},{"Items":[{"ID":101}]},{"Items":[{"ID":101}]},{"Items":[{"ID":101}]},{"Items":[{"ID":101}]},{"Items":[{"ID":101}]},{"Items":[{"ID":101}]},{"Items":[{"ID":101}]},{"Items":[{"ID":101}]},{"Items":[{"ID":101}]},{"Items":[{"ID":101}]},{"Items":[{"ID":101}]},{"Items":[{"ID":101}]},{"Items":[{"ID":101}]},{"Items":[{"ID":101}]},{"Items":[{"ID":101}]},{"Items":[{"ID":101}]},{"Items":[{"ID":101}]},{"Items":[{"ID":101}]},{"Items":[{"ID":101}]},{"Items":[{"ID":101}]},{"Items":[{"ID":101}]},{"Items":[{"ID":101}]},{"Items":[{"ID":101}]},{"Items":[{"ID":101}]},{"Items":[{"ID":101}]},{"Items":[{"ID":101}]},{"Items":[{"ID":101}]},{"Items":[{"ID":101}]},{"Items":[{"ID":101}]},{"Items":[{"ID":101}]},{"Items":[{"ID":101}]},{"Items":[{"ID":101}]},{"Items":[{"ID":101}]},{"Items":[{"ID":101}]},{"Items":[{"ID":101}]},{"Items":[{"ID":101}]},{"Items":[{"ID":101}]},{"Items":[{"ID":101}]},{"Items":[{"ID":101}]},{"Items":[{"ID":101}]},{"Items":[{"ID":101}]},{"Items":[{"ID":101}]},{"Items":[{"ID":101}]},{"Items":[{"ID":101}]},{"Items":[{"ID":101}]},{"Items":[{"ID":101}]},{"Items":[{"ID":101}]},{"Items":[{"ID":101}]},{"Items":[{"ID":377},{"ID":3713}]},{"Items":[{"ID":101}]},{"Items":[{"ID":101}]},{"Items":[{"ID":101}]},{"Items":[{"ID":101}]},{"Items":[{"ID":101}]},{"Items":[{"ID":101}]},{"Items":[{"ID":101}]},{"Items":[{"ID":101}]},{"Items":[{"ID":101}]},{"Items":[{"ID":101}]},{"Items":[{"ID":101}]},{"Items":[{"ID":101}]},{"Items":[{"ID":101}]},{"Items":[{"ID":101}]},{"Items":[{"ID":377},{"ID":3713}]},{"Items":[{"ID":381},{"ID":3716}]},{"Items":[{"ID":101}]},{"Items":[{"ID":101}]},{"Items":[{"ID":101}]},{"Items":[{"ID":101}]},{"Items":[{"ID":101}]},{"Items":[{"ID":101}]},{"Items":[{"ID":101}]},{"Items":[{"ID":101}]},{"Items":[{"ID":101}]},{"Items":[{"ID":101}]},{"Items":[{"ID":101}]},{"Items":[{"ID":101}]},{"Items":[{"ID":101}]},{"Items":[{"ID":101}]},{"Items":[{"ID":373},{"ID":3718}]},{"Items":[{"ID":353}]},{"Items":[{"ID":101}]},{"Items":[{"ID":101}]},{"Items":[{"ID":101}]},{"Items":[{"ID":101}]},{"Items":[{"ID":101}]},{"Items":[{"ID":101}]},{"Items":[{"ID":101}]},{"Items":[{"ID":101}]},{"Items":[{"ID":101}]},{"Items":[{"ID":101}]},{"Items":[{"ID":101}]},{"Items":[{"ID":101}]},{"Items":[{"ID":101}]},{"Items":[{"ID":101}]},{"Items":[{"ID":373},{"ID":3718}]},{"Items":[{"ID":354}]},{"Items":[{"ID":101}]},{"Items":[{"ID":101}]},{"Items":[{"ID":101}]},{"Items":[{"ID":101}]},{"Items":[{"ID":101}]},{"Items":[{"ID":101}]},{"Items":[{"ID":101}]},{"Items":[{"ID":101}]},{"Items":[{"ID":101}]},{"Items":[{"ID":101}]},{"Items":[{"ID":101}]},{"Items":[{"ID":101}]},{"Items":[{"ID":101}]},{"Items":[{"ID":101}]},{"Items":[{"ID":373}]},{"Items":[{"ID":354}]}]}