{"BaseX":32944,"BaseY":32736,"BaseZ":12,"Items":[7350,1705,1709,1704,1703,1708,1713,2188,3409,983,985,1710,12516,989,981,1715,990,979,1711,987,991,1712,980,986,984,4427,1346,12431,12435,6284,1706,8788,1707,12452,12451,1714,8785,12453],"Explored":[65535,65535,65535,65535,65535,65535,65535,65535,65535,65535,65535,65535,65535,65535,65535,65535],"Map":[{"Items":[{"ID":4427}]},{"Items":[{"ID":4427}]},{"Items":[{"ID":4427}]},{"Items":[{"ID":4427}]},{"Items":[{"ID":4427},{"ID":1346},{"ID":12431,"AnimationStep":0}]},{"Items":[{"ID":7350}]},{"Items":[{"ID":7350}]},{"Items":[{"ID":7350}]},{"Items":[{"ID":7350}]},{"Items":[{"ID":7350},{"ID":1346}]},{"Items":[{"ID":7350},{"ID":1708}]},{"Items":[{"ID":7350},{"ID":1705}]},{"Items":[{"ID":7350},{"ID":1705}]},{"Items":[{"ID":7350},{"ID":1709},{"ID":1704}]},{"Items":[{"ID":7350},{"ID":1703}]},{"Items":[{"ID":7350},{"ID":1703}]},{"Items":[{"ID":4427}]},{"Items":[{"ID":4427}]},{"Items":[{"ID":4427}]},{"Items":[{"ID":4427}]},{"Items":[{"ID":4427},{"ID":1346}]},{"Items":[{"ID":7350}]},{"Items":[{"ID":7350}]},{"Items":[{"ID":7350}]},{"Items":[{"ID":7350}]},{"Items":[{"ID":7350},{"ID":1346}]},{"Items":[{"ID":7350}]},{"Items":[{"ID":7350}]},{"Items":[{"ID":7350}]},{"Items":[{"ID":7350},{"ID":1708}]},{"Items":[{"ID":7350},{"ID":1705}]},{"Items":[{"ID":7350},{"ID":1713}]},{"Items":[{"ID":4427}]},{"Items":[{"ID":4427}]},{"Items":[{"ID":4427}]},{"Items":[{"ID":4427}]},{"Items":[{"ID":4427},{"ID":1346},{"ID":12435}]},{"Items":[{"ID":7350},{"ID":6284}]},{"Items":[{"ID":7350}]},{"Items":[{"ID":7350}]},{"Items":[{"ID":7350}]},{"Items":[{"ID":7350},{"ID":1346},{"ID":12431,"AnimationStep":0}]},{"Items":[{"ID":7350},{"ID":1710}]},{"Items":[{"ID":7350}],"Creatures":[{"Header":97,"UKHeader":1073930091,"ID":1073957505,"CreatureType":1,"CharNameLength":18,"CharName":"sandstone scorpion","HealthPercent":100,"Direction":1,"Outfit":398,"ColorHead":0,"ColorBody":0,"ColorLegs":0,"ColorFeet":0,"Addons":0,"Mount":0,"LightRadius":0,"LightColor":0,"Speed":110,"Skull":0,"PartyShield":0,"GuildShield":0,"UKEnd1":0,"UKEnd2":0,"UKEnd3":1,"UKEnd4":0,"UKEnd5":255,"UKEnd6":0,"UKEnd7":0,"UKEnd8":1}]},{"Items":[{"ID":7350},{"ID":2188}]},{"Items":[{"ID":7350}]},{"Items":[{"ID":7350}]},{"Items":[{"ID":7350},{"ID":1704},{"ID":2188}]},{"Items":[{"ID":4427}]},{"Items":[{"ID":4427}]},{"Items":[{"ID":4427}]},{"Items":[{"ID":4427}]},{"Items":[{"ID":4427},{"ID":1346},{"ID":12435}]},{"Items":[{"ID":7350}]},{"Items":[{"ID":7350},{"ID":987}]},{"Items":[{"ID":7350},{"ID":983}]},{"Items":[{"ID":7350},{"ID":985}]},{"Items":[{"ID":7350},{"ID":1346}]},{"Items":[{"ID":7350},{"ID":1706}]},{"Items":[{"ID":7350}]},{"Items":[{"ID":7350}]},{"Items":[{"ID":7350}]},{"Items":[{"ID":7350}]},{"Items":[{"ID":7350},{"ID":1708},{"ID":3409}]},{"Items":[{"ID":4427}]},{"Items":[{"ID":4427}]},{"Items":[{"ID":4427}]},{"Items":[{"ID":4427}]},{"Items":[{"ID":4427},{"ID":1346},{"ID":12435}]},{"Items":[{"ID":7350}]},{"Items":[{"ID":7350},{"ID":980}]},{"Items":[{"ID":7350},{"ID":12516}],"Creatures":[{"Header":97,"UKHeader":1073783988,"ID":1073782439,"CreatureType":1,"CharNameLength":13,"CharName":"crypt defiler","HealthPercent":100,"Direction":0,"Outfit":146,"ColorHead":62,"ColorBody":132,"ColorLegs":42,"ColorFeet":75,"Addons":3,"Mount":0,"LightRadius":0,"LightColor":0,"Speed":95,"Skull":0,"PartyShield":0,"GuildShield":0,"UKEnd1":0,"UKEnd2":0,"UKEnd3":1,"UKEnd4":0,"UKEnd5":255,"UKEnd6":0,"UKEnd7":0,"UKEnd8":1}]},{"Items":[{"ID":7350},{"ID":979}]},{"Items":[{"ID":7350},{"ID":1346},{"ID":8788,"AnimationStep":0}]},{"Items":[{"ID":7350},{"ID":1706}]},{"Items":[{"ID":7350}]},{"Items":[{"ID":7350}]},{"Items":[{"ID":7350}]},{"Items":[{"ID":7350}]},{"Items":[{"ID":7350}]},{"Items":[{"ID":4427}]},{"Items":[{"ID":4427}]},{"Items":[{"ID":4427}]},{"Items":[{"ID":4427}]},{"Items":[{"ID":4427},{"ID":1346},{"ID":12435}]},{"Items":[{"ID":7350}]},{"Items":[{"ID":7350},{"ID":980}]},{"Items":[{"ID":7350},{"ID":12516}]},{"Items":[{"ID":7350},{"ID":979}]},{"Items":[{"ID":7350},{"ID":1346}]},{"Items":[{"ID":7350},{"ID":1709}]},{"Items":[{"ID":7350}]},{"Items":[{"ID":7350}]},{"Items":[{"ID":7350}]},{"Items":[{"ID":7350}]},{"Items":[{"ID":7350}]},{"Items":[{"ID":4427}]},{"Items":[{"ID":4427}]},{"Items":[{"ID":4427}]},{"Items":[{"ID":4427}]},{"Items":[{"ID":4427},{"ID":1346}]},{"Items":[{"ID":7350}]},{"Items":[{"ID":7350},{"ID":980}]},{"Items":[{"ID":7350},{"ID":12516}],"Creatures":[{"Header":97,"UKHeader":0,"ID":1073782440,"CreatureType":1,"CharNameLength":13,"CharName":"crypt defiler","HealthPercent":100,"Direction":0,"Outfit":146,"ColorHead":62,"ColorBody":132,"ColorLegs":42,"ColorFeet":75,"Addons":3,"Mount":0,"LightRadius":0,"LightColor":0,"Speed":95,"Skull":0,"PartyShield":0,"GuildShield":0,"UKEnd1":0,"UKEnd2":0,"UKEnd3":1,"UKEnd4":0,"UKEnd5":255,"UKEnd6":0,"UKEnd7":0,"UKEnd8":1}]},{"Items":[{"ID":7350},{"ID":979}]},{"Items":[{"ID":7350},{"ID":1346}]},{"Items":[{"ID":7350}]},{"Items":[{"ID":7350}]},{"Items":[{"ID":7350}]},{"Items":[{"ID":7350}]},{"Items":[{"ID":7350}]},{"Items":[{"ID":7350}]},{"Items":[{"ID":4427}]},{"Items":[{"ID":4427}]},{"Items":[{"ID":4427}]},{"Items":[{"ID":4427}]},{"Items":[{"ID":4427},{"ID":1346},{"ID":12431,"AnimationStep":0}]},{"Items":[{"ID":7350},{"ID":987}]},{"Items":[{"ID":7350},{"ID":991}]},{"Items":[{"ID":7350},{"ID":12516}]},{"Items":[{"ID":7350},{"ID":979}]},{"Items":[{"ID":7350},{"ID":1346}]},{"Items":[{"ID":7350},{"ID":987}]},{"Items":[{"ID":7350},{"ID":983}]},{"Items":[{"ID":7350},{"ID":983}]},{"Items":[{"ID":7350},{"ID":985}]},{"Items":[{"ID":7350}]},{"Items":[{"ID":7350}]},{"Items":[{"ID":4427}]},{"Items":[{"ID":4427}]},{"Items":[{"ID":4427}]},{"Items":[{"ID":4427}]},{"Items":[{"ID":4427},{"ID":1346}]},{"Items":[{"ID":7350},{"ID":980}]},{"Items":[{"ID":7350},{"ID":12516}]},{"Items":[{"ID":7350},{"ID":12516}]},{"Items":[{"ID":7350},{"ID":979}]},{"Items":[{"ID":7350},{"ID":1711},{"ID":1346},{"ID":12431,"AnimationStep":0}]},{"Items":[{"ID":7350},{"ID":980},{"ID":1707}]},{"Items":[{"ID":7350},{"ID":1710},{"ID":12516}]},{"Items":[{"ID":7350},{"ID":12516},{"ID":2188}]},{"Items":[{"ID":7350},{"ID":989}]},{"Items":[{"ID":7350},{"ID":985}]},{"Items":[{"ID":7350},{"ID":2188}]},{"Items":[{"ID":4427}]},{"Items":[{"ID":4427}]},{"Items":[{"ID":4427}]},{"Items":[{"ID":4427}]},{"Items":[{"ID":4427},{"ID":1346},{"ID":12452}]},{"Items":[{"ID":7350},{"ID":980}]},{"Items":[{"ID":7350},{"ID":12516}]},{"Items":[{"ID":7350},{"ID":1711},{"ID":12516}]},{"Items":[{"ID":7350},{"ID":979},{"ID":1707}]},{"Items":[{"ID":7350},{"ID":1710},{"ID":1704},{"ID":1346}]},{"Items":[{"ID":7350},{"ID":986},{"ID":1703}]},{"Items":[{"ID":7350},{"ID":981},{"ID":1715}]},{"Items":[{"ID":7350},{"ID":990},{"ID":1710}]},{"Items":[{"ID":7350},{"ID":12516}]},{"Items":[{"ID":7350},{"ID":979}]},{"Items":[{"ID":7350},{"ID":1711}]},{"Items":[{"ID":4427}]},{"Items":[{"ID":4427}]},{"Items":[{"ID":4427}]},{"Items":[{"ID":4427}]},{"Items":[{"ID":4427},{"ID":1346},{"ID":12451}]},{"Items":[{"ID":7350},{"ID":980}]},{"Items":[{"ID":7350},{"ID":12516},{"ID":1711}]},{"Items":[{"ID":7350},{"ID":12516},{"ID":1712}]},{"Items":[{"ID":7350},{"ID":979},{"ID":1703}]},{"Items":[{"ID":7350},{"ID":1704},{"ID":1706},{"ID":1346}]},{"Items":[{"ID":7350},{"ID":1703}]},{"Items":[{"ID":7350},{"ID":987},{"ID":1703}]},{"Items":[{"ID":7350},{"ID":991},{"ID":1715}]},{"Items":[{"ID":7350},{"ID":1710},{"ID":12516}]},{"Items":[{"ID":7350},{"ID":989},{"ID":1711}]},{"Items":[{"ID":7350},{"ID":985},{"ID":1712}]},{"Items":[{"ID":4427}]},{"Items":[{"ID":4427}]},{"Items":[{"ID":4427}]},{"Items":[{"ID":4427}]},{"Items":[{"ID":4427},{"ID":1346}]},{"Items":[{"ID":7350},{"ID":980},{"ID":1711}]},{"Items":[{"ID":7350},{"ID":12516},{"ID":1712}]},{"Items":[{"ID":7350},{"ID":12516},{"ID":1703}]},{"Items":[{"ID":7350},{"ID":979},{"ID":1703}]},{"Items":[{"ID":7350},{"ID":1704},{"ID":1706},{"ID":1346}]},{"Items":[{"ID":7350},{"ID":1703}]},{"Items":[{"ID":7350},{"ID":980},{"ID":1703}]},{"Items":[{"ID":7350},{"ID":12516},{"ID":1703}]},{"Items":[{"ID":7350},{"ID":12516},{"ID":1715}]},{"Items":[{"ID":7350},{"ID":12516},{"ID":1712}]},{"Items":[{"ID":7350},{"ID":979},{"ID":1703}]},{"Items":[{"ID":4427}]},{"Items":[{"ID":4427}]},{"Items":[{"ID":4427}]},{"Items":[{"ID":4427}]},{"Items":[{"ID":4427},{"ID":1346}]},{"Items":[{"ID":7350},{"ID":980},{"ID":1704}]},{"Items":[{"ID":7350},{"ID":12516},{"ID":1703}]},{"Items":[{"ID":7350},{"ID":12516},{"ID":1703}]},{"Items":[{"ID":7350},{"ID":979},{"ID":1714}]},{"Items":[{"ID":7350},{"ID":1708},{"ID":1709},{"ID":1346}]},{"Items":[{"ID":7350},{"ID":1713}]},{"Items":[{"ID":7350},{"ID":986},{"ID":1703}]},{"Items":[{"ID":7350},{"ID":981},{"ID":1703}]},{"Items":[{"ID":7350},{"ID":990},{"ID":1703}]},{"Items":[{"ID":7350},{"ID":12516},{"ID":1703}]},{"Items":[{"ID":7350},{"ID":979},{"ID":1703}],"Creatures":[{"Header":97,"UKHeader":1073933534,"ID":1073956051,"CreatureType":1,"CharNameLength":11,"CharName":"grave guard","HealthPercent":100,"Direction":1,"Outfit":234,"ColorHead":0,"ColorBody":0,"ColorLegs":0,"ColorFeet":0,"Addons":0,"Mount":0,"LightRadius":0,"LightColor":0,"Speed":100,"Skull":0,"PartyShield":0,"GuildShield":0,"UKEnd1":0,"UKEnd2":0,"UKEnd3":1,"UKEnd4":0,"UKEnd5":255,"UKEnd6":0,"UKEnd7":0,"UKEnd8":1}]},{"Items":[{"ID":4427}]},{"Items":[{"ID":4427}]},{"Items":[{"ID":4427}]},{"Items":[{"ID":4427}]},{"Items":[{"ID":4427},{"ID":1346}]},{"Items":[{"ID":7350},{"ID":986},{"ID":1704}],"Creatures":[{"Header":97,"UKHeader":0,"ID":1073784015,"CreatureType":1,"CharNameLength":12,"CharName":"grave robber","HealthPercent":100,"Direction":0,"Outfit":146,"ColorHead":57,"ColorBody":95,"ColorLegs":57,"ColorFeet":19,"Addons":3,"Mount":0,"LightRadius":0,"LightColor":0,"Speed":95,"Skull":0,"PartyShield":0,"GuildShield":0,"UKEnd1":0,"UKEnd2":0,"UKEnd3":1,"UKEnd4":0,"UKEnd5":255,"UKEnd6":0,"UKEnd7":0,"UKEnd8":1}]},{"Items":[{"ID":7350},{"ID":981},{"ID":1703}]},{"Items":[{"ID":7350},{"ID":981},{"ID":1714}]},{"Items":[{"ID":7350},{"ID":984},{"ID":1709}]},{"Items":[{"ID":7350},{"ID":1346},{"ID":12431,"AnimationStep":0}]},{"Items":[{"ID":7350},{"ID":1704}]},{"Items":[{"ID":7350},{"ID":1703}]},{"Items":[{"ID":7350},{"ID":1703},{"ID":2188}]},{"Items":[{"ID":7350},{"ID":986},{"ID":1703}]},{"Items":[{"ID":7350},{"ID":981},{"ID":1703}]},{"Items":[{"ID":7350},{"ID":984},{"ID":1703},{"ID":2188}]},{"Items":[{"ID":4427}]},{"Items":[{"ID":4427}]},{"Items":[{"ID":4427}]},{"Items":[{"ID":4427}]},{"Items":[{"ID":4427},{"ID":1346},{"ID":12431,"AnimationStep":0}]},{"Items":[{"ID":7350},{"ID":1712}]},{"Items":[{"ID":7350},{"ID":1703}]},{"Items":[{"ID":7350},{"ID":1706}]},{"Items":[{"ID":7350}]},{"Items":[{"ID":7350},{"ID":1346}]},{"Items":[{"ID":7350},{"ID":1708}]},{"Items":[{"ID":7350},{"ID":1713}]},{"Items":[{"ID":7350},{"ID":1703}]},{"Items":[{"ID":7350},{"ID":1703}]},{"Items":[{"ID":7350},{"ID":1703}]},{"Items":[{"ID":7350},{"ID":1703}]},{"Items":[{"ID":4427}]},{"Items":[{"ID":4427}]},{"Items":[{"ID":4427}]},{"Items":[{"ID":4427}]},{"Items":[{"ID":4427},{"ID":1346},{"ID":8785,"AnimationStep":0}]},{"Items":[{"ID":7350},{"ID":1703}]},{"Items":[{"ID":7350},{"ID":1703}]},{"Items":[{"ID":7350},{"ID":1706}]},{"Items":[{"ID":7350}]},{"Items":[{"ID":7350},{"ID":1346},{"ID":12453}]},{"Items":[{"ID":7350}]},{"Items":[{"ID":7350},{"ID":1708}]},{"Items":[{"ID":7350},{"ID":1713}]},{"Items":[{"ID":7350},{"ID":1703}]},{"Items":[{"ID":7350},{"ID":1703}]},{"Items":[{"ID":7350},{"ID":1703}]}]}