{"BaseX":33440,"BaseY":32064,"BaseZ":10,"Items":[1128,4462,15044,4460,15045,10605,15623,15627,15630,15631,15628,15622,15629,15625,15043,15040,4466,1345,2733,9285,11256,19318,2730,15046,15042,15620,15621,283,3031,15626,11425,11423,11424,1855,10821,10675,15041,11418,1866,11421,10681,1865,10832,10836,284,10833,10820,12355,11411,11412,11410,11416,1854,1867,10829,10679,11417,3453,11406,11405,2115,1858,11422,11420,11047,11414,10677,11409,10678,1857,11408,11407,11415,11413,285,11419,3359,1856],"Explored":[65535,65535,65535,65535,65535,65535,65535,65535,65535,65535,65535,65535,65535,65535,65535,65535],"Map":[{"Items":[{"ID":1128}]},{"Items":[{"ID":1128}]},{"Items":[{"ID":1128}]},{"Items":[{"ID":1128}]},{"Items":[{"ID":1128},{"ID":4462}]},{"Items":[{"ID":15044},{"ID":4460}]},{"Items":[{"ID":15045}]},{"Items":[{"ID":10605},{"ID":15623},{"ID":15627}]},{"Items":[{"ID":10605},{"ID":15630},{"ID":15631},{"ID":15628}]},{"Items":[{"ID":10605},{"ID":15622},{"ID":15629}]},{"Items":[{"ID":10605},{"ID":15625},{"ID":15631}]},{"Items":[{"ID":15043}]},{"Items":[{"ID":15040},{"ID":4462}]},{"Items":[{"ID":15044},{"ID":4466}]},{"Items":[{"ID":1128}]},{"Items":[{"ID":1128}]},{"Items":[{"ID":1128},{"ID":1345},{"ID":2733},{"ID":9285},{"ID":11256}]},{"Items":[{"ID":1128},{"ID":1345},{"ID":19318},{"ID":2730},{"ID":11256}]},{"Items":[{"ID":1128},{"ID":1345},{"ID":11256}]},{"Items":[{"ID":1128},{"ID":1345},{"ID":11256}]},{"Items":[{"ID":1128},{"ID":1345},{"ID":9285},{"ID":11256}]},{"Items":[{"ID":15046},{"ID":1345},{"ID":19318},{"ID":11256}]},{"Items":[{"ID":15042},{"ID":1345},{"ID":11256}]},{"Items":[{"ID":15043}]},{"Items":[{"ID":10605},{"ID":15620},{"ID":15621},{"ID":283,"Count":1},{"ID":3031,"Count":16}]},{"Items":[{"ID":15040},{"ID":283,"Count":8}]},{"Items":[{"ID":10605},{"ID":15627},{"ID":15620}]},{"Items":[{"ID":15046}]},{"Items":[{"ID":15044}]},{"Items":[{"ID":1128},{"ID":15626},{"ID":1345},{"ID":11256}]},{"Items":[{"ID":1128},{"ID":1345},{"ID":2733},{"ID":9285},{"ID":11256}]},{"Items":[{"ID":1128},{"ID":1345},{"ID":2730},{"ID":11256}]},{"Items":[{"ID":11425}]},{"Items":[{"ID":11423}]},{"Items":[{"ID":11424},{"ID":1855}]},{"Items":[{"ID":11423}]},{"Items":[{"ID":11425}]},{"Items":[{"ID":11425},{"ID":10821},{"ID":10675}]},{"Items":[{"ID":10605},{"ID":15629}]},{"Items":[{"ID":10605},{"ID":15623}]},{"Items":[{"ID":10605},{"ID":15620},{"ID":15630}]},{"Items":[{"ID":15044},{"ID":1855}]},{"Items":[{"ID":15041}]},{"Items":[{"ID":15043}]},{"Items":[{"ID":15043},{"ID":283,"Count":1}]},{"Items":[{"ID":11418},{"ID":15621}]},{"Items":[{"ID":11424}]},{"Items":[{"ID":11424},{"ID":1866}]},{"Items":[{"ID":11425}],"Creatures":[{"Header":97,"UKHeader":1073801836,"ID":1073801835,"CreatureType":1,"CharNameLength":5,"CharName":"demon","HealthPercent":100,"Direction":1,"Outfit":35,"ColorHead":0,"ColorBody":0,"ColorLegs":0,"ColorFeet":0,"Addons":0,"Mount":0,"LightRadius":0,"LightColor":0,"Speed":128,"Skull":0,"PartyShield":0,"GuildShield":0,"UKEnd1":0,"UKEnd2":0,"UKEnd3":1,"UKEnd4":0,"UKEnd5":255,"UKEnd6":0,"UKEnd7":0,"UKEnd8":1}]},{"Items":[{"ID":11424}]},{"Items":[{"ID":11421},{"ID":10681}]},{"Items":[{"ID":11425}]},{"Items":[{"ID":11418},{"ID":1865}]},{"Items":[{"ID":11424},{"ID":10832}]},{"Items":[{"ID":11421},{"ID":10836},{"ID":284,"Count":7}]},{"Items":[{"ID":11424},{"ID":10833}]},{"Items":[{"ID":11425},{"ID":10820},{"ID":15620}]},{"Items":[{"ID":15045}]},{"Items":[{"ID":15043},{"ID":283,"Count":27}]},{"Items":[{"ID":15042},{"ID":284,"Count":100},{"ID":1855}]},{"Items":[{"ID":11425},{"ID":15626},{"ID":284,"Count":97}]},{"Items":[{"ID":12355},{"ID":11411},{"ID":11412},{"ID":15630},{"ID":284,"Count":56}]},{"Items":[{"ID":12355},{"ID":11410},{"ID":11416}]},{"Items":[{"ID":11425}]},{"Items":[{"ID":11425}]},{"Items":[{"ID":11424}],"Creatures":[{"Header":97,"UKHeader":1073802355,"ID":1073801838,"CreatureType":1,"CharNameLength":11,"CharName":"grim reaper","HealthPercent":100,"Direction":1,"Outfit":300,"ColorHead":0,"ColorBody":0,"ColorLegs":0,"ColorFeet":0,"Addons":1,"Mount":0,"LightRadius":0,"LightColor":0,"Speed":160,"Skull":0,"PartyShield":0,"GuildShield":0,"UKEnd1":0,"UKEnd2":0,"UKEnd3":1,"UKEnd4":0,"UKEnd5":255,"UKEnd6":0,"UKEnd7":0,"UKEnd8":1}]},{"Items":[{"ID":11425}]},{"Items":[{"ID":11418},{"ID":1854}]},{"Items":[{"ID":11423}]},{"Items":[{"ID":11424},{"ID":1867}]},{"Items":[{"ID":11425},{"ID":10832}]},{"Items":[{"ID":11424},{"ID":10829},{"ID":283,"Count":1},{"ID":10679}]},{"Items":[{"ID":11421},{"ID":15629},{"ID":1866}]},{"Items":[{"ID":11417},{"ID":15625},{"ID":283,"Count":1}]},{"Items":[{"ID":15042},{"ID":3453},{"ID":3031,"Count":20}]},{"Items":[{"ID":11424},{"ID":15626},{"ID":284,"Count":9},{"ID":1866}]},{"Items":[{"ID":11425},{"ID":15630}]},{"Items":[{"ID":11424},{"ID":10675}]},{"Items":[{"ID":12355},{"ID":11406},{"ID":11405}]},{"Items":[{"ID":11425}]},{"Items":[{"ID":11424}]},{"Items":[{"ID":11425}]},{"Items":[{"ID":11424},{"ID":2115,"AnimationStep":0},{"ID":2115,"AnimationStep":0}]},{"Items":[{"ID":11425}]},{"Items":[{"ID":11425}]},{"Items":[{"ID":11423},{"ID":1858}]},{"Items":[{"ID":11422}]},{"Items":[{"ID":11424}]},{"Items":[{"ID":11417},{"ID":2115,"AnimationStep":0},{"ID":2115,"AnimationStep":0}]},{"Items":[{"ID":11425},{"ID":15629},{"ID":1865}]},{"Items":[{"ID":11423},{"ID":15623}]},{"Items":[{"ID":11423},{"ID":15630}]},{"Items":[{"ID":11420}]},{"Items":[{"ID":11424},{"ID":11047,"AnimationStep":0}]},{"Items":[{"ID":12355},{"ID":11414},{"ID":11412}]},{"Items":[{"ID":12355},{"ID":11410},{"ID":11416},{"ID":1866}]},{"Items":[{"ID":11425},{"ID":10677}]},{"Items":[{"ID":11425}]},{"Items":[{"ID":11425},{"ID":1858}]},{"Items":[{"ID":11423}]},{"Items":[{"ID":11424}]},{"Items":[{"ID":11424}]},{"Items":[{"ID":11418},{"ID":1855}]},{"Items":[{"ID":11424}]},{"Items":[{"ID":11423}]},{"Items":[{"ID":11421}]},{"Items":[{"ID":12355},{"ID":11411},{"ID":11412},{"ID":284,"Count":1},{"ID":10677}]},{"Items":[{"ID":12355},{"ID":11410},{"ID":11409},{"ID":1867}]},{"Items":[{"ID":11417},{"ID":10675}]},{"Items":[{"ID":11417},{"ID":10679}]},{"Items":[{"ID":11424}]},{"Items":[{"ID":12355},{"ID":11412},{"ID":11409}]},{"Items":[{"ID":11423}]},{"Items":[{"ID":12355},{"ID":11411},{"ID":11412}]},{"Items":[{"ID":12355},{"ID":11410},{"ID":11416}]},{"Items":[{"ID":11418},{"ID":10677}]},{"Items":[{"ID":11417}]},{"Items":[{"ID":11423}]},{"Items":[{"ID":11425}]},{"Items":[{"ID":11417}]},{"Items":[{"ID":12355},{"ID":11411},{"ID":11412}]},{"Items":[{"ID":12355},{"ID":11410},{"ID":11409}]},{"Items":[{"ID":11425}]},{"Items":[{"ID":11425},{"ID":10678}]},{"Items":[{"ID":11423}]},{"Items":[{"ID":11423}]},{"Items":[{"ID":11423}]},{"Items":[{"ID":11424}],"Creatures":[{"Header":97,"UKHeader":1073802354,"ID":1073801841,"CreatureType":1,"CharNameLength":5,"CharName":"demon","HealthPercent":100,"Direction":1,"Outfit":35,"ColorHead":0,"ColorBody":0,"ColorLegs":0,"ColorFeet":0,"Addons":0,"Mount":0,"LightRadius":0,"LightColor":0,"Speed":128,"Skull":0,"PartyShield":0,"GuildShield":0,"UKEnd1":0,"UKEnd2":0,"UKEnd3":1,"UKEnd4":0,"UKEnd5":255,"UKEnd6":0,"UKEnd7":0,"UKEnd8":1}]},{"Items":[{"ID":11424}]},{"Items":[{"ID":11424},{"ID":11047,"AnimationStep":0}]},{"Items":[{"ID":12355},{"ID":11414},{"ID":11412}]},{"Items":[{"ID":12355},{"ID":11410},{"ID":11416}]},{"Items":[{"ID":11424},{"ID":283,"Count":2}]},{"Items":[{"ID":12355},{"ID":11411},{"ID":283,"Count":1},{"ID":1858}]},{"Items":[{"ID":12355},{"ID":11410}]},{"Items":[{"ID":11417}]},{"Items":[{"ID":11425}]},{"Items":[{"ID":11425},{"ID":11047,"AnimationStep":0}]},{"Items":[{"ID":12355},{"ID":11411},{"ID":11412}]},{"Items":[{"ID":12355},{"ID":11410},{"ID":11409}]},{"Items":[{"ID":11424}]},{"Items":[{"ID":11425}]},{"Items":[{"ID":11421}]},{"Items":[{"ID":11425},{"ID":1857}]},{"Items":[{"ID":11417}]},{"Items":[{"ID":11424}]},{"Items":[{"ID":11425}]},{"Items":[{"ID":12355},{"ID":11414},{"ID":11412}]},{"Items":[{"ID":12355},{"ID":11408},{"ID":11407},{"ID":284,"Count":14}]},{"Items":[{"ID":12355},{"ID":11415},{"ID":11416},{"ID":11413},{"ID":1854}]},{"Items":[{"ID":12355},{"ID":11409},{"ID":1857}]},{"Items":[{"ID":11417},{"ID":284,"Count":1},{"ID":1855},{"ID":10678}]},{"Items":[{"ID":11425},{"ID":283,"Count":1}]},{"Items":[{"ID":11424}]},{"Items":[{"ID":11424},{"ID":284,"Count":1}]},{"Items":[{"ID":11417}]},{"Items":[{"ID":12355},{"ID":11411},{"ID":11409},{"ID":10681}]},{"Items":[{"ID":11418}]},{"Items":[{"ID":11424}]},{"Items":[{"ID":11425}]},{"Items":[{"ID":11424},{"ID":285,"Count":100}]},{"Items":[{"ID":11423}]},{"Items":[{"ID":11424}]},{"Items":[{"ID":11423}]},{"Items":[{"ID":11425},{"ID":284,"Count":4},{"ID":283,"Count":1},{"ID":1858}]},{"Items":[{"ID":12355},{"ID":11406},{"ID":11405}]},{"Items":[{"ID":11425}]},{"Items":[{"ID":11425},{"ID":1867}]},{"Items":[{"ID":11425},{"ID":284,"Count":1}]},{"Items":[{"ID":11423}]},{"Items":[{"ID":11417}]},{"Items":[{"ID":11424}]},{"Items":[{"ID":11424}]},{"Items":[{"ID":12355},{"ID":11411},{"ID":11410}]},{"Items":[{"ID":11425}]},{"Items":[{"ID":11425}]},{"Items":[{"ID":11424}]},{"Items":[{"ID":11425},{"ID":11047,"AnimationStep":0}]},{"Items":[{"ID":11417}]},{"Items":[{"ID":11419}]},{"Items":[{"ID":12355},{"ID":11411},{"ID":11413}]},{"Items":[{"ID":12355},{"ID":11415},{"ID":11409}]},{"Items":[{"ID":11422}]},{"Items":[{"ID":11424},{"ID":284,"Count":1}]},{"Items":[{"ID":11420}]},{"Items":[{"ID":11424},{"ID":11047,"AnimationStep":0}]},{"Items":[{"ID":11424}]},{"Items":[{"ID":11422}]},{"Items":[{"ID":11417},{"ID":284,"Count":2}]},{"Items":[{"ID":12355},{"ID":11412},{"ID":11409}]},{"Items":[{"ID":11424}]},{"Items":[{"ID":11425}]},{"Items":[{"ID":11425}]},{"Items":[{"ID":11423}]},{"Items":[{"ID":11417}]},{"Items":[{"ID":11419}]},{"Items":[{"ID":12355},{"ID":11412},{"ID":11409}]},{"Items":[{"ID":11424}]},{"Items":[{"ID":11425}]},{"Items":[{"ID":11423},{"ID":10677}]},{"Items":[{"ID":11417}]},{"Items":[{"ID":11424}]},{"Items":[{"ID":11417}]},{"Items":[{"ID":11424}]},{"Items":[{"ID":11425}],"Creatures":[{"Header":97,"UKHeader":1073814655,"ID":1073801840,"CreatureType":1,"CharNameLength":11,"CharName":"grim reaper","HealthPercent":100,"Direction":1,"Outfit":300,"ColorHead":0,"ColorBody":0,"ColorLegs":0,"ColorFeet":0,"Addons":1,"Mount":0,"LightRadius":0,"LightColor":0,"Speed":160,"Skull":0,"PartyShield":0,"GuildShield":0,"UKEnd1":0,"UKEnd2":0,"UKEnd3":1,"UKEnd4":0,"UKEnd5":255,"UKEnd6":0,"UKEnd7":0,"UKEnd8":1}]},{"Items":[{"ID":11423}]},{"Items":[{"ID":11425},{"ID":10675}]},{"Items":[{"ID":11425},{"ID":1866}]},{"Items":[{"ID":11421}]},{"Items":[{"ID":11424}]},{"Items":[{"ID":11424}]},{"Items":[{"ID":11419}]},{"Items":[{"ID":11425},{"ID":1865}]},{"Items":[{"ID":11424}]},{"Items":[{"ID":12355},{"ID":11411},{"ID":11409},{"ID":1857}]},{"Items":[{"ID":11420}]},{"Items":[{"ID":11423}]},{"Items":[{"ID":11425}]},{"Items":[{"ID":11425}]},{"Items":[{"ID":11425}]},{"Items":[{"ID":11418}]},{"Items":[{"ID":11425}]},{"Items":[{"ID":11424},{"ID":10679}]},{"Items":[{"ID":11425}]},{"Items":[{"ID":12355},{"ID":11410},{"ID":11409}]},{"Items":[{"ID":11425}]},{"Items":[{"ID":11425},{"ID":2115,"AnimationStep":0},{"ID":2115,"AnimationStep":0}]},{"Items":[{"ID":11424},{"ID":3359},{"ID":3031,"Count":19},{"ID":3359},{"ID":3359},{"ID":3359},{"ID":3359},{"ID":3359},{"ID":3359},{"ID":3359}]},{"Items":[{"ID":11423}]},{"Items":[{"ID":11424}]},{"Items":[{"ID":11425}]},{"Items":[{"ID":12355},{"ID":11411},{"ID":11410}]},{"Items":[{"ID":11421},{"ID":2115,"AnimationStep":0},{"ID":2115,"AnimationStep":0}]},{"Items":[{"ID":11424}]},{"Items":[{"ID":11423},{"ID":284,"Count":3},{"ID":1867}]},{"Items":[{"ID":11423},{"ID":1858}]},{"Items":[{"ID":11425}]},{"Items":[{"ID":11417},{"ID":11047,"AnimationStep":0}]},{"Items":[{"ID":11424}]},{"Items":[{"ID":11417}]},{"Items":[{"ID":11425},{"ID":284,"Count":1}]},{"Items":[{"ID":11421},{"ID":284,"Count":1},{"ID":1856}]},{"Items":[{"ID":11425},{"ID":1857}]},{"Items":[{"ID":11424}]},{"Items":[{"ID":11419},{"ID":1857}]},{"Items":[{"ID":11425},{"ID":1866}]},{"Items":[{"ID":11425}]},{"Items":[{"ID":12355},{"ID":11412},{"ID":11409}]},{"Items":[{"ID":11425}]},{"Items":[{"ID":12355},{"ID":11411}]},{"Items":[{"ID":12355},{"ID":11408},{"ID":11413}]},{"Items":[{"ID":12355},{"ID":11408},{"ID":11407}]},{"Items":[{"ID":12355},{"ID":11410},{"ID":11409}]},{"Items":[{"ID":11424}]},{"Items":[{"ID":11424}]},{"Items":[{"ID":11417}]}]}