{"BaseX":32400,"BaseY":32192,"BaseZ":10,"Items":[101,5726,5718,5717,5715,5713,5714,4609,5649,4611,5716],"Explored":[65535,65535,65532,65520,65520,65504,65504,65504,65024,49152,49152,49152,0,0,0,0],"Map":[{"Items":[{"ID":101}]},{"Items":[{"ID":101}]},{"Items":[{"ID":101}]},{"Items":[{"ID":5726}]},{"Items":[{"ID":5726}]},{"Items":[{"ID":101}]},{"Items":[{"ID":5718}]},{"Items":[{"ID":101}]},{"Items":[{"ID":5717}]},{"Items":[{"ID":101}]},{"Items":[{"ID":101}]},{"Items":[{"ID":101}]},{"Items":[{"ID":101}]},{"Items":[{"ID":101}]},{"Items":[{"ID":101}]},{"Items":[{"ID":101}]},{"Items":[{"ID":101}]},{"Items":[{"ID":5726}]},{"Items":[{"ID":101}]},{"Items":[{"ID":101}]},{"Items":[{"ID":5726}]},{"Items":[{"ID":101}]},{"Items":[{"ID":101}]},{"Items":[{"ID":101}]},{"Items":[{"ID":101}]},{"Items":[{"ID":101}]},{"Items":[{"ID":101}]},{"Items":[{"ID":101}]},{"Items":[{"ID":101}]},{"Items":[{"ID":101}]},{"Items":[{"ID":101}]},{"Items":[{"ID":101}]},{"Items":[{"ID":101}]},{"Items":[{"ID":101}]},{"Items":[{"ID":101}]},{"Items":[{"ID":101}]},{"Items":[{"ID":101}]},{"Items":[{"ID":101}]},{"Items":[{"ID":101}]},{"Items":[{"ID":101}]},{"Items":[{"ID":101}]},{"Items":[{"ID":101}]},{"Items":[{"ID":101}]},{"Items":[{"ID":101}]},{"Items":[{"ID":101}]},{"Items":[{"ID":101}]},{"Items":[{"ID":5717}]},{"Items":[{"ID":101}]},{"Items":[{"ID":101}]},{"Items":[{"ID":101}]},{"Items":[{"ID":101}]},{"Items":[{"ID":101}]},{"Items":[{"ID":101}]},{"Items":[{"ID":101}]},{"Items":[{"ID":101}]},{"Items":[{"ID":101}]},{"Items":[{"ID":101}]},{"Items":[{"ID":101}]},{"Items":[{"ID":101}]},{"Items":[{"ID":101}]},{"Items":[{"ID":101}]},{"Items":[{"ID":101}]},{"Items":[{"ID":101}]},{"Items":[{"ID":101}]},{"Items":[{"ID":101}]},{"Items":[{"ID":101}]},{"Items":[{"ID":101}]},{"Items":[{"ID":101}]},{"Items":[{"ID":101}]},{"Items":[{"ID":101}]},{"Items":[{"ID":5726}]},{"Items":[{"ID":101}]},{"Items":[{"ID":5715}]},{"Items":[{"ID":5726}]},{"Items":[{"ID":5713}]},{"Items":[{"ID":101}]},{"Items":[{"ID":101}]},{"Items":[{"ID":101}]},{"Items":[{"ID":101}]},{"Items":[{"ID":101}]},{"Items":[{"ID":101}]},{"Items":[{"ID":5714}]},{"Items":[{"ID":5726}]},{"Items":[{"ID":101}]},{"Items":[{"ID":5714}]},{"Items":[{"ID":5713}]},{"Items":[{"ID":101}]},{"Items":[{"ID":101}]},{"Items":[{"ID":101}]},{"Items":[{"ID":101}]},{"Items":[{"ID":101}]},{"Items":[{"ID":101}]},{"Items":[{"ID":4609,"AnimationStep":0},{"ID":5649}]},{"Items":[{"ID":101}]},{"Items":[{"ID":101}]},{"Items":[{"ID":101}]},{"Items":[{"ID":5726}]},{"Items":[{"ID":5714}]},{"Items":[{"ID":101}]},{"Items":[{"ID":101}]},{"Items":[{"ID":101}]},{"Items":[{"ID":101}]},{"Items":[{"ID":101}]},{"Items":[{"ID":4611,"AnimationStep":0},{"ID":5649}]},{"Items":[{"ID":101}]},{"Items":[{"ID":101}]},{"Items":[{"ID":5716}]},{"Items":[{"ID":101}]},{"Items":[{"ID":101}]},{"Items":[{"ID":101}]},{"Items":[{"ID":101}]},{"Items":[{"ID":101}]},{"Items":[{"ID":101}]},{"Items":[{"ID":101}]},{"Items":[{"ID":101}]},{"Items":[{"ID":101}]}]}