{"BaseX":32352,"BaseY":32144,"BaseZ":11,"Items":[4427,1295,368,1294,1298,2153,1301,4786,1948,4790,385,4785,1299,1300,4006,3264,1780,1772,4273,4145,1297,101,1791,4423,4425,5631,4568,4666,8880,5618,8878,5637,4561,4416,4562,4662,4421,4563,4419,4426,5714,4567,4659,4660,5712],"Explored":[65535,65535,65535,65535,65535,65535,65535,65535,65535,65535,65535,65535,65535,65535,65535,65535],"Map":[{"Items":[{"ID":4427}]},{"Items":[{"ID":4427},{"ID":1295}]},{"Items":[{"ID":368}]},{"Items":[{"ID":368}]},{"Items":[{"ID":368}]},{"Items":[{"ID":368}]},{"Items":[{"ID":368}]},{"Items":[{"ID":368}]},{"Items":[{"ID":368}]},{"Items":[{"ID":368}]},{"Items":[{"ID":368}]},{"Items":[{"ID":368}]},{"Items":[{"ID":368}]},{"Items":[{"ID":368}]},{"Items":[{"ID":368}]},{"Items":[{"ID":368}]},{"Items":[{"ID":4427},{"ID":1294}]},{"Items":[{"ID":4427},{"ID":1298}]},{"Items":[{"ID":368}]},{"Items":[{"ID":368},{"ID":2153}]},{"Items":[{"ID":368}]},{"Items":[{"ID":368}]},{"Items":[{"ID":368}]},{"Items":[{"ID":368}]},{"Items":[{"ID":368},{"ID":1301}]},{"Items":[{"ID":368},{"ID":1294}]},{"Items":[{"ID":368},{"ID":1294}]},{"Items":[{"ID":368},{"ID":1294}]},{"Items":[{"ID":368},{"ID":1294}]},{"Items":[{"ID":368}]},{"Items":[{"ID":368}]},{"Items":[{"ID":368}]},{"Items":[{"ID":368}]},{"Items":[{"ID":368}]},{"Items":[{"ID":368}]},{"Items":[{"ID":368}]},{"Items":[{"ID":368}]},{"Items":[{"ID":368}]},{"Items":[{"ID":368}]},{"Items":[{"ID":368}],"Creatures":[{"Header":97,"UKHeader":0,"ID":1074652531,"CreatureType":1,"CharNameLength":7,"CharName":"rotworm","HealthPercent":100,"Direction":0,"Outfit":26,"ColorHead":0,"ColorBody":0,"ColorLegs":0,"ColorFeet":0,"Addons":0,"Mount":0,"LightRadius":0,"LightColor":0,"Speed":116,"Skull":0,"PartyShield":0,"GuildShield":0,"UKEnd1":0,"UKEnd2":0,"UKEnd3":1,"UKEnd4":0,"UKEnd5":0,"UKEnd6":0,"UKEnd7":0,"UKEnd8":0}]},{"Items":[{"ID":368},{"ID":1295}]},{"Items":[{"ID":368},{"ID":4786},{"ID":1948}]},{"Items":[{"ID":368},{"ID":4790}],"Creatures":[{"Header":97,"UKHeader":0,"ID":1074657268,"CreatureType":1,"CharNameLength":7,"CharName":"rotworm","HealthPercent":100,"Direction":0,"Outfit":26,"ColorHead":0,"ColorBody":0,"ColorLegs":0,"ColorFeet":0,"Addons":0,"Mount":0,"LightRadius":0,"LightColor":0,"Speed":116,"Skull":0,"PartyShield":0,"GuildShield":0,"UKEnd1":0,"UKEnd2":0,"UKEnd3":1,"UKEnd4":0,"UKEnd5":0,"UKEnd6":0,"UKEnd7":0,"UKEnd8":0}]},{"Items":[{"ID":368}]},{"Items":[{"ID":368}]},{"Items":[{"ID":368}]},{"Items":[{"ID":368}]},{"Items":[{"ID":368}]},{"Items":[{"ID":368}]},{"Items":[{"ID":368}]},{"Items":[{"ID":368}]},{"Items":[{"ID":368}]},{"Items":[{"ID":368}]},{"Items":[{"ID":368}]},{"Items":[{"ID":368}]},{"Items":[{"ID":368}]},{"Items":[{"ID":368},{"ID":1295}]},{"Items":[{"ID":385}]},{"Items":[{"ID":368},{"ID":4785}]},{"Items":[{"ID":368}]},{"Items":[{"ID":368}]},{"Items":[{"ID":368}]},{"Items":[{"ID":368}]},{"Items":[{"ID":368}]},{"Items":[{"ID":368},{"ID":1294}]},{"Items":[{"ID":368},{"ID":1299}]},{"Items":[{"ID":368}]},{"Items":[{"ID":368}]},{"Items":[{"ID":368}]},{"Items":[{"ID":368}]},{"Items":[{"ID":368}]},{"Items":[{"ID":368}]},{"Items":[{"ID":368},{"ID":1300}]},{"Items":[{"ID":368},{"ID":1294}]},{"Items":[{"ID":368},{"ID":1294}]},{"Items":[{"ID":368},{"ID":1294}]},{"Items":[{"ID":368},{"ID":1294}]},{"Items":[{"ID":368}]},{"Items":[{"ID":368}]},{"Items":[{"ID":368}]},{"Items":[{"ID":4427}]},{"Items":[{"ID":4427},{"ID":1295}]},{"Items":[{"ID":368}]},{"Items":[{"ID":368},{"ID":2153}]},{"Items":[{"ID":368}]},{"Items":[{"ID":368},{"ID":4006}]},{"Items":[{"ID":368}]},{"Items":[{"ID":368},{"ID":4006}]},{"Items":[{"ID":368}]},{"Items":[{"ID":368}]},{"Items":[{"ID":368}]},{"Items":[{"ID":368}]},{"Items":[{"ID":368}]},{"Items":[{"ID":368}]},{"Items":[{"ID":368}]},{"Items":[{"ID":368}]},{"Items":[{"ID":4427}]},{"Items":[{"ID":4427},{"ID":1295}]},{"Items":[{"ID":368}]},{"Items":[{"ID":368}]},{"Items":[{"ID":368}]},{"Items":[{"ID":368}]},{"Items":[{"ID":368},{"ID":3264}]},{"Items":[{"ID":368},{"ID":4006}]},{"Items":[{"ID":368}]},{"Items":[{"ID":368}]},{"Items":[{"ID":368}]},{"Items":[{"ID":368}]},{"Items":[{"ID":368}]},{"Items":[{"ID":368}]},{"Items":[{"ID":368}]},{"Items":[{"ID":368}]},{"Items":[{"ID":4427}]},{"Items":[{"ID":4427},{"ID":1295}]},{"Items":[{"ID":368}]},{"Items":[{"ID":368}]},{"Items":[{"ID":368}]},{"Items":[{"ID":368}]},{"Items":[{"ID":368}]},{"Items":[{"ID":368}]},{"Items":[{"ID":368}]},{"Items":[{"ID":368}]},{"Items":[{"ID":368}]},{"Items":[{"ID":368}]},{"Items":[{"ID":368}]},{"Items":[{"ID":368}]},{"Items":[{"ID":368}]},{"Items":[{"ID":368}]},{"Items":[{"ID":4427}]},{"Items":[{"ID":4427},{"ID":1295}]},{"Items":[{"ID":368}]},{"Items":[{"ID":368}]},{"Items":[{"ID":368}]},{"Items":[{"ID":368}]},{"Items":[{"ID":368}]},{"Items":[{"ID":368}]},{"Items":[{"ID":368}]},{"Items":[{"ID":368}]},{"Items":[{"ID":368}]},{"Items":[{"ID":368}]},{"Items":[{"ID":368}]},{"Items":[{"ID":368}]},{"Items":[{"ID":368}]},{"Items":[{"ID":368}]},{"Items":[{"ID":4427}]},{"Items":[{"ID":4427},{"ID":1295}]},{"Items":[{"ID":368}]},{"Items":[{"ID":368}]},{"Items":[{"ID":368}]},{"Items":[{"ID":368}]},{"Items":[{"ID":368}]},{"Items":[{"ID":368}]},{"Items":[{"ID":368},{"ID":4006}],"Creatures":[{"Header":97,"UKHeader":0,"ID":1074656220,"CreatureType":1,"CharNameLength":7,"CharName":"rotworm","HealthPercent":100,"Direction":0,"Outfit":26,"ColorHead":0,"ColorBody":0,"ColorLegs":0,"ColorFeet":0,"Addons":0,"Mount":0,"LightRadius":0,"LightColor":0,"Speed":116,"Skull":0,"PartyShield":0,"GuildShield":0,"UKEnd1":0,"UKEnd2":0,"UKEnd3":1,"UKEnd4":0,"UKEnd5":0,"UKEnd6":0,"UKEnd7":0,"UKEnd8":0}]},{"Items":[{"ID":368}]},{"Items":[{"ID":368}]},{"Items":[{"ID":368}]},{"Items":[{"ID":368}]},{"Items":[{"ID":368}]},{"Items":[{"ID":368}]},{"Items":[{"ID":368}]},{"Items":[{"ID":4427}]},{"Items":[{"ID":4427},{"ID":1295}]},{"Items":[{"ID":368}]},{"Items":[{"ID":368},{"ID":2153}]},{"Items":[{"ID":368}]},{"Items":[{"ID":368}]},{"Items":[{"ID":368}]},{"Items":[{"ID":368}]},{"Items":[{"ID":368},{"ID":2153}]},{"Items":[{"ID":368},{"ID":1780}]},{"Items":[{"ID":368}]},{"Items":[{"ID":368}]},{"Items":[{"ID":368},{"ID":2153}]},{"Items":[{"ID":368}]},{"Items":[{"ID":368}]},{"Items":[{"ID":368}]},{"Items":[{"ID":4427}]},{"Items":[{"ID":4427},{"ID":1295}]},{"Items":[{"ID":368}]},{"Items":[{"ID":368}]},{"Items":[{"ID":368}]},{"Items":[{"ID":368}]},{"Items":[{"ID":368}]},{"Items":[{"ID":368},{"ID":1772}]},{"Items":[{"ID":368}]},{"Items":[{"ID":368},{"ID":4006},{"ID":4273}]},{"Items":[{"ID":368},{"ID":4145}]},{"Items":[{"ID":368}]},{"Items":[{"ID":368}]},{"Items":[{"ID":368}]},{"Items":[{"ID":368}]},{"Items":[{"ID":368}]},{"Items":[{"ID":4427}]},{"Items":[{"ID":4427},{"ID":1297}]},{"Items":[{"ID":368},{"ID":1294}]},{"Items":[{"ID":368},{"ID":1294}]},{"Items":[{"ID":368},{"ID":1294}]},{"Items":[{"ID":101},{"ID":1294}]},{"Items":[{"ID":368},{"ID":1294}]},{"Items":[{"ID":368},{"ID":1294}]},{"Items":[{"ID":368},{"ID":1791}]},{"Items":[{"ID":368},{"ID":4006}]},{"Items":[{"ID":368}]},{"Items":[{"ID":368},{"ID":1294}]},{"Items":[{"ID":368},{"ID":1294}]},{"Items":[{"ID":368},{"ID":1294}]},{"Items":[{"ID":368},{"ID":1294}]},{"Items":[{"ID":368},{"ID":1294}]},{"Items":[{"ID":4427}]},{"Items":[{"ID":4427}]},{"Items":[{"ID":4427}]},{"Items":[{"ID":4427}]},{"Items":[{"ID":4427}]},{"Items":[{"ID":101},{"ID":4423},{"ID":4425}]},{"Items":[{"ID":101},{"ID":4423},{"ID":4425}]},{"Items":[{"ID":101},{"ID":4423},{"ID":4425},{"ID":5631}]},{"Items":[{"ID":4568},{"ID":4666},{"ID":8880},{"ID":5618}]},{"Items":[{"ID":368},{"ID":4006}]},{"Items":[{"ID":368}]},{"Items":[{"ID":368},{"ID":8878},{"ID":5637}]},{"Items":[{"ID":4427}]},{"Items":[{"ID":4427}]},{"Items":[{"ID":4427}]},{"Items":[{"ID":4427}]},{"Items":[{"ID":101},{"ID":4423},{"ID":4425}]},{"Items":[{"ID":101}]},{"Items":[{"ID":101}]},{"Items":[{"ID":101}]},{"Items":[{"ID":101}]},{"Items":[{"ID":101}]},{"Items":[{"ID":101},{"ID":4423}]},{"Items":[{"ID":4561},{"ID":4416},{"ID":5631}]},{"Items":[{"ID":4562},{"ID":4662},{"ID":4421}]},{"Items":[{"ID":4563},{"ID":4666}]},{"Items":[{"ID":368}]},{"Items":[{"ID":368},{"ID":4419},{"ID":5637}]},{"Items":[{"ID":101},{"ID":4426}]},{"Items":[{"ID":101}]},{"Items":[{"ID":101}]},{"Items":[{"ID":4427}]},{"Items":[{"ID":101},{"ID":4416}]},{"Items":[{"ID":101},{"ID":4416}]},{"Items":[{"ID":101},{"ID":4416}]},{"Items":[{"ID":101},{"ID":4416}]},{"Items":[{"ID":101},{"ID":4416}]},{"Items":[{"ID":5714},{"ID":4416}]},{"Items":[{"ID":101},{"ID":4421}]},{"Items":[{"ID":4561},{"ID":5631}]},{"Items":[{"ID":4561}]},{"Items":[{"ID":4563},{"ID":4662}]},{"Items":[{"ID":4567},{"ID":4659},{"ID":4273}]},{"Items":[{"ID":4561},{"ID":4660},{"ID":5637}]},{"Items":[{"ID":101},{"ID":4419}]},{"Items":[{"ID":101},{"ID":4416}]},{"Items":[{"ID":5712},{"ID":4416}]},{"Items":[{"ID":101},{"ID":4426}]}]}