{"BaseX":33376,"BaseY":31936,"BaseZ":13,"Items":[1128,353,4466,351,4465,352,4461,10534,756,4464,317,323,318,319,758,760,4458,305,354,1857,355,2891,4462,1867,2888,17431,20982,20990,1866,1856,4113,1852,320,759,4463,1858],"Explored":[65535,65535,65535,65535,65535,65535,65535,65535,65535,65535,65535,65535,65535,65535,65535,65535],"Map":[{"Items":[{"ID":1128}]},{"Items":[{"ID":1128}]},{"Items":[{"ID":1128}]},{"Items":[{"ID":1128}]},{"Items":[{"ID":1128}]},{"Items":[{"ID":1128}]},{"Items":[{"ID":1128}]},{"Items":[{"ID":1128}]},{"Items":[{"ID":1128}]},{"Items":[{"ID":1128}]},{"Items":[{"ID":1128}]},{"Items":[{"ID":1128}]},{"Items":[{"ID":1128}]},{"Items":[{"ID":1128}]},{"Items":[{"ID":1128}]},{"Items":[{"ID":1128}]},{"Items":[{"ID":1128}]},{"Items":[{"ID":1128}]},{"Items":[{"ID":1128}]},{"Items":[{"ID":1128}]},{"Items":[{"ID":1128}]},{"Items":[{"ID":1128}]},{"Items":[{"ID":1128}]},{"Items":[{"ID":1128}]},{"Items":[{"ID":1128}]},{"Items":[{"ID":1128}]},{"Items":[{"ID":1128}]},{"Items":[{"ID":1128}]},{"Items":[{"ID":1128}]},{"Items":[{"ID":1128}]},{"Items":[{"ID":1128}]},{"Items":[{"ID":1128}]},{"Items":[{"ID":1128}]},{"Items":[{"ID":1128}]},{"Items":[{"ID":1128}]},{"Items":[{"ID":1128}]},{"Items":[{"ID":1128}]},{"Items":[{"ID":1128}]},{"Items":[{"ID":1128}]},{"Items":[{"ID":1128}]},{"Items":[{"ID":1128}]},{"Items":[{"ID":1128}]},{"Items":[{"ID":1128}]},{"Items":[{"ID":1128}]},{"Items":[{"ID":1128}]},{"Items":[{"ID":1128}]},{"Items":[{"ID":1128}]},{"Items":[{"ID":1128}]},{"Items":[{"ID":1128}]},{"Items":[{"ID":1128}]},{"Items":[{"ID":1128}]},{"Items":[{"ID":1128}]},{"Items":[{"ID":1128}]},{"Items":[{"ID":1128}]},{"Items":[{"ID":1128}]},{"Items":[{"ID":1128}]},{"Items":[{"ID":1128}]},{"Items":[{"ID":1128}]},{"Items":[{"ID":1128}]},{"Items":[{"ID":1128}]},{"Items":[{"ID":1128}]},{"Items":[{"ID":1128}]},{"Items":[{"ID":1128}]},{"Items":[{"ID":1128}]},{"Items":[{"ID":1128}]},{"Items":[{"ID":1128}]},{"Items":[{"ID":1128}]},{"Items":[{"ID":1128}]},{"Items":[{"ID":1128}]},{"Items":[{"ID":1128}]},{"Items":[{"ID":1128}]},{"Items":[{"ID":1128}]},{"Items":[{"ID":1128}]},{"Items":[{"ID":1128}]},{"Items":[{"ID":1128}]},{"Items":[{"ID":1128}]},{"Items":[{"ID":1128}]},{"Items":[{"ID":1128}]},{"Items":[{"ID":1128}]},{"Items":[{"ID":1128}]},{"Items":[{"ID":1128}]},{"Items":[{"ID":1128}]},{"Items":[{"ID":1128}]},{"Items":[{"ID":1128}]},{"Items":[{"ID":351},{"ID":4465}]},{"Items":[{"ID":352},{"ID":4461}]},{"Items":[{"ID":353},{"ID":4461}]},{"Items":[{"ID":351},{"ID":4466}]},{"Items":[{"ID":1128}]},{"Items":[{"ID":1128}]},{"Items":[{"ID":1128}]},{"Items":[{"ID":1128}]},{"Items":[{"ID":1128}]},{"Items":[{"ID":1128}]},{"Items":[{"ID":1128}]},{"Items":[{"ID":1128}]},{"Items":[{"ID":352},{"ID":4461}]},{"Items":[{"ID":10534},{"ID":4461}]},{"Items":[{"ID":10534},{"ID":4461}]},{"Items":[{"ID":10534},{"ID":756},{"ID":4461}]},{"Items":[{"ID":352},{"ID":4464}]},{"Items":[{"ID":351}]},{"Items":[{"ID":351}]},{"Items":[{"ID":352}]},{"Items":[{"ID":352},{"ID":4461}]},{"Items":[{"ID":352},{"ID":4466}]},{"Items":[{"ID":1128}]},{"Items":[{"ID":1128}]},{"Items":[{"ID":1128}]},{"Items":[{"ID":1128}]},{"Items":[{"ID":1128}]},{"Items":[{"ID":1128}]},{"Items":[{"ID":10534},{"ID":317},{"ID":323}]},{"Items":[{"ID":10534},{"ID":318},{"ID":319}]},{"Items":[{"ID":10534},{"ID":758}]},{"Items":[{"ID":10534},{"ID":760}]},{"Items":[{"ID":351}]},{"Items":[{"ID":351}]},{"Items":[{"ID":351}]},{"Items":[{"ID":353}]},{"Items":[{"ID":352}]},{"Items":[{"ID":351},{"ID":4458}]},{"Items":[{"ID":1128}]},{"Items":[{"ID":1128}]},{"Items":[{"ID":1128}]},{"Items":[{"ID":1128}]},{"Items":[{"ID":1128}]},{"Items":[{"ID":1128}]},{"Items":[{"ID":352}]},{"Items":[{"ID":10534},{"ID":305}]},{"Items":[{"ID":10534},{"ID":756}]},{"Items":[{"ID":354}]},{"Items":[{"ID":353}]},{"Items":[{"ID":352}]},{"Items":[{"ID":352}]},{"Items":[{"ID":351},{"ID":1857}]},{"Items":[{"ID":351}]},{"Items":[{"ID":353}]},{"Items":[{"ID":354},{"ID":4461}]},{"Items":[{"ID":354},{"ID":4461}]},{"Items":[{"ID":353},{"ID":4466}]},{"Items":[{"ID":1128}]},{"Items":[{"ID":1128}]},{"Items":[{"ID":1128}]},{"Items":[{"ID":10534},{"ID":317},{"ID":319}]},{"Items":[{"ID":10534},{"ID":318},{"ID":758}]},{"Items":[{"ID":10534},{"ID":760}]},{"Items":[{"ID":351}]},{"Items":[{"ID":354}]},{"Items":[{"ID":351}]},{"Items":[{"ID":353}]},{"Items":[{"ID":352}]},{"Items":[{"ID":354}]},{"Items":[{"ID":352}]},{"Items":[{"ID":355}]},{"Items":[{"ID":354},{"ID":2891,"Splash":5}]},{"Items":[{"ID":351},{"ID":4462}]},{"Items":[{"ID":352},{"ID":4461}]},{"Items":[{"ID":353},{"ID":4466}]},{"Items":[{"ID":1128}]},{"Items":[{"ID":10534},{"ID":305}]},{"Items":[{"ID":10534},{"ID":756}]},{"Items":[{"ID":353}]},{"Items":[{"ID":351}]},{"Items":[{"ID":354}]},{"Items":[{"ID":355}]},{"Items":[{"ID":352},{"ID":1867}]},{"Items":[{"ID":352}]},{"Items":[{"ID":352}]},{"Items":[{"ID":352}]},{"Items":[{"ID":351},{"ID":2888,"Splash":5},{"ID":17431}],"Creatures":[{"Header":97,"UKHeader":1074060946,"ID":1074063122,"CreatureType":1,"CharNameLength":11,"CharName":"blood beast","HealthPercent":100,"Direction":0,"Outfit":602,"ColorHead":0,"ColorBody":0,"ColorLegs":0,"ColorFeet":0,"Addons":0,"Mount":0,"LightRadius":0,"LightColor":0,"Speed":110,"Skull":0,"PartyShield":0,"GuildShield":0,"UKEnd1":0,"UKEnd2":0,"UKEnd3":1,"UKEnd4":0,"UKEnd5":255,"UKEnd6":0,"UKEnd7":0,"UKEnd8":1}]},{"Items":[{"ID":355},{"ID":2888,"Splash":6},{"ID":20982}]},{"Items":[{"ID":354},{"ID":2891,"Splash":6}]},{"Items":[{"ID":351}]},{"Items":[{"ID":352},{"ID":4462}]},{"Items":[{"ID":353},{"ID":4466}]},{"Items":[{"ID":10534},{"ID":318}]},{"Items":[{"ID":10534},{"ID":756},{"ID":1857}]},{"Items":[{"ID":351}]},{"Items":[{"ID":354}]},{"Items":[{"ID":351}]},{"Items":[{"ID":351}]},{"Items":[{"ID":351}]},{"Items":[{"ID":352}]},{"Items":[{"ID":351}]},{"Items":[{"ID":354}]},{"Items":[{"ID":355},{"ID":2888,"Splash":6},{"ID":20990},{"ID":1866}]},{"Items":[{"ID":352},{"ID":2891,"Splash":5}]},{"Items":[{"ID":351}]},{"Items":[{"ID":351}]},{"Items":[{"ID":352}]},{"Items":[{"ID":354},{"ID":4462}]},{"Items":[{"ID":10534}]},{"Items":[{"ID":10534},{"ID":756}]},{"Items":[{"ID":355}]},{"Items":[{"ID":352}]},{"Items":[{"ID":351},{"ID":1856}]},{"Items":[{"ID":354},{"ID":1856}],"Creatures":[{"Header":97,"UKHeader":1073800939,"ID":1074059794,"CreatureType":1,"CharNameLength":11,"CharName":"blood beast","HealthPercent":100,"Direction":0,"Outfit":602,"ColorHead":0,"ColorBody":0,"ColorLegs":0,"ColorFeet":0,"Addons":0,"Mount":0,"LightRadius":0,"LightColor":0,"Speed":110,"Skull":0,"PartyShield":0,"GuildShield":0,"UKEnd1":0,"UKEnd2":0,"UKEnd3":1,"UKEnd4":0,"UKEnd5":255,"UKEnd6":0,"UKEnd7":0,"UKEnd8":1}]},{"Items":[{"ID":353}]},{"Items":[{"ID":354}]},{"Items":[{"ID":351},{"ID":1866}]},{"Items":[{"ID":353}]},{"Items":[{"ID":351},{"ID":2891,"Splash":6},{"ID":20990}]},{"Items":[{"ID":351},{"ID":2891,"Splash":5},{"ID":17431}]},{"Items":[{"ID":354},{"ID":2888,"Splash":5},{"ID":4113}]},{"Items":[{"ID":354}]},{"Items":[{"ID":354}]},{"Items":[{"ID":354}]},{"Items":[{"ID":10534}]},{"Items":[{"ID":10534},{"ID":756},{"ID":1867}]},{"Items":[{"ID":351}]},{"Items":[{"ID":354}]},{"Items":[{"ID":351}]},{"Items":[{"ID":353},{"ID":1852}]},{"Items":[{"ID":353}]},{"Items":[{"ID":353}]},{"Items":[{"ID":353}]},{"Items":[{"ID":353}]},{"Items":[{"ID":355}]},{"Items":[{"ID":351}]},{"Items":[{"ID":351}]},{"Items":[{"ID":353}]},{"Items":[{"ID":351}]},{"Items":[{"ID":353}]},{"Items":[{"ID":10534}]},{"Items":[{"ID":10534},{"ID":320}]},{"Items":[{"ID":10534},{"ID":759}]},{"Items":[{"ID":355}]},{"Items":[{"ID":352}]},{"Items":[{"ID":352}]},{"Items":[{"ID":353}]},{"Items":[{"ID":354}]},{"Items":[{"ID":354}]},{"Items":[{"ID":351}]},{"Items":[{"ID":351}]},{"Items":[{"ID":351}]},{"Items":[{"ID":353}]},{"Items":[{"ID":351}]},{"Items":[{"ID":351}]},{"Items":[{"ID":353}]},{"Items":[{"ID":10534},{"ID":323},{"ID":4463}]},{"Items":[{"ID":10534},{"ID":319},{"ID":758}]},{"Items":[{"ID":10534},{"ID":760}]},{"Items":[{"ID":354}]},{"Items":[{"ID":352}]},{"Items":[{"ID":351}]},{"Items":[{"ID":353}]},{"Items":[{"ID":351}]},{"Items":[{"ID":352},{"ID":1858}]},{"Items":[{"ID":351}]},{"Items":[{"ID":352}]},{"Items":[{"ID":355},{"ID":2891,"Splash":5}]},{"Items":[{"ID":354}]},{"Items":[{"ID":353}]},{"Items":[{"ID":352}]},{"Items":[{"ID":352},{"ID":1867}]}]}