{"BaseX":32592,"BaseY":32736,"BaseZ":5,"Items":[1199,1197,1202,1200,1205,1203,1512,1539,2908,1517,486,482,1968,1513,872,1536,6459],"Explored":[65528,65528,65528,65528,65528,65528,65528,65528,65528,65528,0,0,127,127,127,127],"Map":[{"Items":[{"ID":1199}]},{"Items":[{"ID":1197}]},{"Items":[{"ID":1197}]},{"Items":[{"ID":1197}]},{"Items":[{"ID":1197}]},{"Items":[{"ID":1197}]},{"Items":[{"ID":1197}]},{"Items":[{"ID":1197}]},{"Items":[{"ID":1197}]},{"Items":[{"ID":1197}]},{"Items":[{"ID":1197}]},{"Items":[{"ID":1197}]},{"Items":[{"ID":1202}]},{"Items":[{"ID":1199}]},{"Items":[{"ID":1197}]},{"Items":[{"ID":1197}]},{"Items":[{"ID":1197}]},{"Items":[{"ID":1197}]},{"Items":[{"ID":1197}]},{"Items":[{"ID":1197}]},{"Items":[{"ID":1197}]},{"Items":[{"ID":1197}]},{"Items":[{"ID":1197}]},{"Items":[{"ID":1197}]},{"Items":[{"ID":1197}]},{"Items":[{"ID":1202}]},{"Items":[{"ID":1199}]},{"Items":[{"ID":1197}]},{"Items":[{"ID":1197}]},{"Items":[{"ID":1197}]},{"Items":[{"ID":1197}]},{"Items":[{"ID":1197}]},{"Items":[{"ID":1197}]},{"Items":[{"ID":1197}]},{"Items":[{"ID":1197}]},{"Items":[{"ID":1197}]},{"Items":[{"ID":1197}]},{"Items":[{"ID":1197}]},{"Items":[{"ID":1202}]},{"Items":[{"ID":1199}]},{"Items":[{"ID":1197}]},{"Items":[{"ID":1197}]},{"Items":[{"ID":1197}]},{"Items":[{"ID":1197}]},{"Items":[{"ID":1197}]},{"Items":[{"ID":1197}]},{"Items":[{"ID":1197}]},{"Items":[{"ID":1197}]},{"Items":[{"ID":1197}]},{"Items":[{"ID":1197}]},{"Items":[{"ID":1197}]},{"Items":[{"ID":1202}]},{"Items":[{"ID":1199}]},{"Items":[{"ID":1197}]},{"Items":[{"ID":1197}]},{"Items":[{"ID":1197}]},{"Items":[{"ID":1197}]},{"Items":[{"ID":1197}]},{"Items":[{"ID":1197}]},{"Items":[{"ID":1197}]},{"Items":[{"ID":1197}]},{"Items":[{"ID":1197}]},{"Items":[{"ID":1197}]},{"Items":[{"ID":1197}]},{"Items":[{"ID":1202}]},{"Items":[{"ID":1199}]},{"Items":[{"ID":1197}]},{"Items":[{"ID":1197}]},{"Items":[{"ID":1197}]},{"Items":[{"ID":1197}]},{"Items":[{"ID":1197}]},{"Items":[{"ID":1197}]},{"Items":[{"ID":1197}]},{"Items":[{"ID":1197}]},{"Items":[{"ID":1197}]},{"Items":[{"ID":1197}]},{"Items":[{"ID":1197}]},{"Items":[{"ID":1202}]},{"Items":[{"ID":1199}]},{"Items":[{"ID":1197}]},{"Items":[{"ID":1197}]},{"Items":[{"ID":1197}]},{"Items":[{"ID":1197}]},{"Items":[{"ID":1197}]},{"Items":[{"ID":1197}]},{"Items":[{"ID":1197}]},{"Items":[{"ID":1197}]},{"Items":[{"ID":1197}]},{"Items":[{"ID":1197}]},{"Items":[{"ID":1197}]},{"Items":[{"ID":1202}]},{"Items":[{"ID":1199}]},{"Items":[{"ID":1197}]},{"Items":[{"ID":1197}]},{"Items":[{"ID":1197}]},{"Items":[{"ID":1197}]},{"Items":[{"ID":1197}]},{"Items":[{"ID":1197}]},{"Items":[{"ID":1197}]},{"Items":[{"ID":1197}]},{"Items":[{"ID":1197}]},{"Items":[{"ID":1197}]},{"Items":[{"ID":1197}]},{"Items":[{"ID":1202}]},{"Items":[{"ID":1199}]},{"Items":[{"ID":1197}]},{"Items":[{"ID":1197}]},{"Items":[{"ID":1197}]},{"Items":[{"ID":1197}]},{"Items":[{"ID":1197}]},{"Items":[{"ID":1197}]},{"Items":[{"ID":1197}]},{"Items":[{"ID":1197}]},{"Items":[{"ID":1197}]},{"Items":[{"ID":1197}]},{"Items":[{"ID":1197}]},{"Items":[{"ID":1202}]},{"Items":[{"ID":1200}]},{"Items":[{"ID":1205}]},{"Items":[{"ID":1205}]},{"Items":[{"ID":1205}]},{"Items":[{"ID":1205}]},{"Items":[{"ID":1205}]},{"Items":[{"ID":1205}]},{"Items":[{"ID":1205}]},{"Items":[{"ID":1205}]},{"Items":[{"ID":1205}]},{"Items":[{"ID":1205}]},{"Items":[{"ID":1205}]},{"Items":[{"ID":1203}]},{"Items":[{"ID":1512}]},{"Items":[{"ID":1539}]},{"Items":[{"ID":1512}]},{"Items":[{"ID":1539},{"ID":2908,"AnimationStep":0}]},{"Items":[{"ID":1512}]},{"Items":[{"ID":1539}]},{"Items":[{"ID":1517}]},{"Items":[{"ID":486}]},{"Items":[{"ID":482}]},{"Items":[{"ID":486},{"ID":1968}]},{"Items":[{"ID":486}]},{"Items":[{"ID":486}]},{"Items":[{"ID":486}]},{"Items":[{"ID":486},{"ID":1513}]},{"Items":[{"ID":486}]},{"Items":[{"ID":486}]},{"Items":[{"ID":486},{"ID":872}]},{"Items":[{"ID":486},{"ID":872}]},{"Items":[{"ID":486}]},{"Items":[{"ID":486}]},{"Items":[{"ID":486},{"ID":1536}]},{"Items":[{"ID":486}]},{"Items":[{"ID":486},{"ID":872}]},{"Items":[{"ID":486}]},{"Items":[{"ID":486}]},{"Items":[{"ID":486},{"ID":872}]},{"Items":[{"ID":486}]},{"Items":[{"ID":486},{"ID":6459}]}]}